[{"patternid":1,"pattern":{"id":0,"feature":8,"split":0}},
{"patternid":2,"pattern":{"id":0,"feature":11,"split":13}},
{"patternid":3,"pattern":{"id":0,"feature":4,"split":8}},
{"patternid":4,"pattern":{"id":0,"feature":4,"split":0}},
{"patternid":5,"pattern":{"id":0,"feature":8,"split":1}},
{"patternid":6,"pattern":{"id":0,"feature":3,"split":9}},
{"patternid":7,"pattern":{"id":0,"feature":1,"split":13}},
{"patternid":8,"pattern":{"id":0,"feature":12,"split":9}},
{"patternid":9,"pattern":{"id":0,"feature":15,"split":11}},
{"patternid":10,"pattern":{"id":0,"feature":3,"split":2}},
{"patternid":11,"pattern":{"id":0,"feature":11,"split":12}},
{"patternid":12,"pattern":{"id":0,"feature":15,"split":10}},
{"patternid":13,"pattern":{"id":0,"feature":2,"split":9}},
{"patternid":14,"pattern":{"id":0,"feature":13,"split":12}},
{"patternid":15,"pattern":{"id":0,"feature":10,"split":4}},
{"patternid":16,"pattern":{"id":0,"feature":0,"split":1}},
{"patternid":17,"pattern":{"id":0,"feature":10,"split":3}},
{"patternid":18,"pattern":{"id":0,"feature":9,"split":3}},
{"patternid":19,"pattern":{"id":0,"feature":2,"split":3}},
{"patternid":20,"pattern":{"id":0,"feature":1,"split":6}},
{"patternid":21,"pattern":{"id":0,"feature":2,"split":1}},
{"patternid":22,"pattern":{"id":0,"feature":7,"split":9}},
{"patternid":23,"pattern":{"id":0,"feature":1,"split":11}},
{"patternid":24,"pattern":{"id":0,"feature":13,"split":9}},
{"patternid":25,"pattern":{"id":0,"feature":1,"split":4}},
{"patternid":26,"pattern":{"id":0,"feature":4,"split":1}},
{"patternid":27,"pattern":{"id":0,"feature":10,"split":12}},
{"patternid":28,"pattern":{"id":0,"feature":5,"split":2}},
{"patternid":29,"pattern":{"id":0,"feature":1,"split":5}},
{"patternid":30,"pattern":{"id":0,"feature":6,"split":12}},
{"patternid":31,"pattern":{"id":0,"feature":3,"split":1}},
{"patternid":32,"pattern":{"id":0,"feature":2,"split":5}},
{"patternid":33,"pattern":{"id":0,"feature":11,"split":3}},
{"patternid":34,"pattern":{"id":0,"feature":2,"split":2}},
{"patternid":35,"pattern":{"id":0,"feature":4,"split":6}},
{"patternid":36,"pattern":{"id":0,"feature":0,"split":7}},
{"patternid":37,"pattern":{"id":0,"feature":1,"split":3}},
{"patternid":38,"pattern":{"id":0,"feature":0,"split":9}},
{"patternid":39,"pattern":{"id":0,"feature":13,"split":5}},
{"patternid":40,"pattern":{"id":0,"feature":13,"split":4}},
{"patternid":41,"pattern":{"id":0,"feature":4,"split":7}},
{"patternid":42,"pattern":{"id":0,"feature":10,"split":2}},
{"patternid":43,"pattern":{"id":0,"feature":8,"split":3}},
{"patternid":44,"pattern":{"id":0,"feature":7,"split":4}},
{"patternid":45,"pattern":{"id":0,"feature":0,"split":5}},
{"patternid":46,"pattern":{"id":0,"prediction":[]}},
{"patternid":47,"pattern":{"id":0,"feature":10,"split":1}},
{"patternid":48,"pattern":{"id":0,"feature":14,"split":2}},
{"patternid":49,"pattern":{"id":0,"feature":6,"split":6}},
{"patternid":50,"pattern":{"id":0,"feature":14,"split":4}},
{"patternid":51,"pattern":{"id":0,"feature":0,"split":4}},
{"patternid":52,"pattern":{"id":0,"feature":8,"split":5}},
{"patternid":53,"pattern":{"id":0,"feature":6,"split":2}},
{"patternid":54,"pattern":{"id":0,"feature":7,"split":2}},
{"patternid":55,"pattern":{"id":0,"feature":1,"split":8}},
{"patternid":56,"pattern":{"id":0,"feature":3,"split":5}},
{"patternid":57,"pattern":{"id":0,"feature":5,"split":10}},
{"patternid":58,"pattern":{"id":0,"feature":4,"split":2}},
{"patternid":59,"pattern":{"id":0,"feature":15,"split":7}},
{"patternid":60,"pattern":{"id":0,"feature":6,"split":3}},
{"patternid":61,"pattern":{"id":0,"feature":14,"split":1}},
{"patternid":62,"pattern":{"id":0,"feature":9,"split":9}},
{"patternid":63,"pattern":{"id":0,"feature":8,"split":7}},
{"patternid":64,"pattern":{"id":0,"feature":9,"split":10}},
{"patternid":65,"pattern":{"id":0,"feature":4,"split":3}},
{"patternid":66,"pattern":{"id":0,"feature":6,"split":4}},
{"patternid":67,"pattern":{"id":0,"feature":15,"split":8}},
{"patternid":68,"pattern":{"id":0,"feature":2,"split":7}},
{"patternid":69,"pattern":{"id":0,"feature":12,"split":1}},
{"patternid":70,"pattern":{"id":0,"feature":5,"split":5}},
{"patternid":71,"pattern":{"id":0,"feature":14,"split":3}},
{"patternid":72,"pattern":{"id":0,"feature":3,"split":6}},
{"patternid":73,"pattern":{"id":0,"feature":13,"split":6}},
{"patternid":74,"pattern":{"id":0,"feature":7,"split":1}},
{"patternid":75,"pattern":{"id":0,"feature":11,"split":9}},
{"patternid":76,"pattern":{"id":0,"feature":12,"split":8}},
{"patternid":77,"pattern":{"id":0,"feature":2,"split":8}},
{"patternid":78,"pattern":{"id":0,"feature":7,"split":3}},
{"patternid":79,"pattern":{"id":0,"feature":13,"split":7}},
{"patternid":80,"pattern":{"id":0,"feature":4,"split":5}},
{"patternid":81,"pattern":{"id":0,"feature":0,"split":6}},
{"patternid":82,"pattern":{"id":0,"feature":12,"split":4}},
{"patternid":83,"pattern":{"id":0,"feature":15,"split":9}},
{"patternid":84,"pattern":{"id":0,"feature":3,"split":7}},
{"patternid":85,"pattern":{"id":0,"feature":10,"split":8}},
{"patternid":86,"pattern":{"id":0,"feature":6,"split":8}},
{"patternid":87,"pattern":{"id":0,"feature":8,"split":2}},
{"patternid":88,"pattern":{"id":0,"feature":10,"split":7}},
{"patternid":89,"pattern":{"id":0,"feature":10,"split":5}},
{"patternid":90,"pattern":{"id":0,"feature":9,"split":7}},
{"patternid":91,"pattern":{"id":0,"feature":0,"split":3}},
{"patternid":92,"pattern":{"id":0,"feature":9,"split":6}},
{"patternid":93,"pattern":{"id":0,"feature":12,"split":2}},
{"patternid":94,"pattern":{"id":0,"feature":5,"split":7}},
{"patternid":95,"pattern":{"id":0,"feature":9,"split":13}},
{"patternid":96,"pattern":{"id":0,"feature":5,"split":6}},
{"patternid":97,"pattern":{"id":0,"feature":14,"split":0}},
{"patternid":98,"pattern":{"id":0,"feature":1,"split":10}},
{"patternid":99,"pattern":{"id":0,"feature":3,"split":3}},
{"patternid":100,"pattern":{"id":0,"feature":7,"split":5}},
{"patternid":101,"pattern":{"id":0,"feature":12,"split":6}},
{"patternid":102,"pattern":{"id":0,"feature":5,"split":9}},
{"patternid":103,"pattern":{"id":0,"feature":1,"split":12}},
{"patternid":104,"pattern":{"id":0,"feature":14,"split":7}},
{"patternid":105,"pattern":{"id":0,"feature":12,"split":5}},
{"patternid":106,"pattern":{"id":0,"feature":2,"split":6}},
{"patternid":107,"pattern":{"id":0,"feature":10,"split":6}},
{"patternid":108,"pattern":{"id":0,"feature":4,"split":4}},
{"patternid":109,"pattern":{"id":0,"feature":9,"split":5}},
{"patternid":110,"pattern":{"id":0,"feature":13,"split":8}},
{"patternid":111,"pattern":{"id":0,"feature":11,"split":7}},
{"patternid":112,"pattern":{"id":0,"feature":11,"split":11}},
{"patternid":113,"pattern":{"id":0,"feature":11,"split":8}},
{"patternid":114,"pattern":{"id":0,"feature":11,"split":6}},
{"patternid":115,"pattern":{"id":0,"feature":0,"split":2}},
{"patternid":116,"pattern":{"id":0,"feature":11,"split":5}},
{"patternid":117,"pattern":{"id":0,"feature":11,"split":4}},
{"patternid":118,"pattern":{"id":0,"feature":15,"split":5}},
{"patternid":119,"pattern":{"id":0,"feature":8,"split":6}},
{"patternid":120,"pattern":{"id":0,"feature":8,"split":4}},
{"patternid":121,"pattern":{"id":0,"feature":15,"split":6}},
{"patternid":122,"pattern":{"id":0,"feature":1,"split":7}},
{"patternid":123,"pattern":{"id":0,"feature":9,"split":11}},
{"patternid":124,"pattern":{"id":0,"feature":13,"split":11}},
{"patternid":125,"pattern":{"id":0,"feature":13,"split":10}},
{"patternid":126,"pattern":{"id":0,"feature":12,"split":3}},
{"patternid":127,"pattern":{"id":0,"feature":7,"split":6}},
{"patternid":128,"pattern":{"id":0,"feature":5,"split":8}},
{"patternid":129,"pattern":{"id":0,"feature":14,"split":6}},
{"patternid":130,"pattern":{"id":0,"feature":14,"split":5}},
{"patternid":131,"pattern":{"id":0,"feature":6,"split":9}},
{"patternid":132,"pattern":{"id":0,"feature":7,"split":7}},
{"patternid":133,"pattern":{"id":0,"feature":11,"split":10}},
{"patternid":134,"pattern":{"id":0,"feature":7,"split":0}},
{"patternid":135,"pattern":{"id":0,"feature":9,"split":12}},
{"patternid":136,"pattern":{"id":0,"feature":9,"split":8}},
{"patternid":137,"pattern":{"id":0,"feature":6,"split":5}},
{"patternid":138,"pattern":{"id":0,"feature":5,"split":4}},
{"patternid":139,"pattern":{"id":0,"feature":5,"split":3}},
{"patternid":140,"pattern":{"id":0,"feature":14,"split":8}},
{"patternid":141,"pattern":{"id":0,"feature":8,"split":8}},
{"patternid":142,"pattern":{"id":0,"feature":8,"split":9}},
{"patternid":143,"pattern":{"id":0,"feature":7,"split":8}},
{"patternid":144,"pattern":{"id":0,"feature":3,"split":8}},
{"patternid":145,"pattern":{"id":0,"feature":6,"split":10}},
{"patternid":146,"pattern":{"id":0,"feature":6,"split":7}},
{"patternid":147,"pattern":{"id":0,"feature":12,"split":7}},
{"patternid":148,"pattern":{"id":0,"feature":10,"split":10}},
{"patternid":149,"pattern":{"id":0,"feature":9,"split":4}},
{"patternid":150,"pattern":{"id":0,"feature":10,"split":11}},
{"patternid":151,"pattern":{"id":0,"feature":3,"split":4}},
{"patternid":152,"pattern":{"id":0,"feature":10,"split":9}},
{"patternid":153,"pattern":{"id":0,"feature":0,"split":8}},
{"patternid":154,"pattern":{"id":0,"feature":12,"split":0}},
{"patternid":155,"pattern":{"id":0,"feature":15,"split":4}},
{"patternid":156,"pattern":{"id":0,"feature":6,"split":11}},
{"patternid":157,"pattern":{"id":0,"feature":1,"split":9}},
{"patternid":158,"pattern":{"id":0,"feature":2,"split":4}},
{"patternid":211,"pattern":{"id":0,"feature":10,"split":2,"leftChild":{"id":1,"feature":8,"split":3}}},
{"patternid":210,"pattern":{"id":0,"feature":14,"split":2,"rightChild":{"id":1,"feature":14,"split":4}}},
{"patternid":209,"pattern":{"id":0,"feature":14,"split":4,"rightChild":{"id":1,"feature":9,"split":5}}},
{"patternid":208,"pattern":{"id":0,"feature":14,"split":4,"leftChild":{"id":1,"feature":10,"split":5}}},
{"patternid":207,"pattern":{"id":0,"feature":15,"split":8,"rightChild":{"id":1,"feature":11,"split":7}}},
{"patternid":206,"pattern":{"id":0,"feature":12,"split":1,"rightChild":{"id":1,"feature":14,"split":3}}},
{"patternid":205,"pattern":{"id":0,"feature":12,"split":1,"rightChild":{"id":1,"feature":15,"split":8}}},
{"patternid":204,"pattern":{"id":0,"feature":7,"split":3,"rightChild":{"id":1,"feature":13,"split":8}}},
{"patternid":203,"pattern":{"id":0,"feature":10,"split":5,"leftChild":{"id":1,"feature":13,"split":7}}},
{"patternid":202,"pattern":{"id":0,"feature":11,"split":8,"rightChild":{"id":1,"feature":5,"split":7}}}]