[{"patternid":1,"pattern":{"id":0,"feature":10,"split":10}},
{"patternid":2,"pattern":{"id":0,"feature":8,"split":6}},
{"patternid":3,"pattern":{"id":0,"feature":7,"split":8}},
{"patternid":4,"pattern":{"id":0,"feature":3,"split":5}},
{"patternid":5,"pattern":{"id":0,"feature":10,"split":11}},
{"patternid":6,"pattern":{"id":0,"feature":12,"split":9}},
{"patternid":7,"pattern":{"id":0,"feature":14,"split":6}},
{"patternid":8,"pattern":{"id":0,"feature":5,"split":4}},
{"patternid":9,"pattern":{"id":0,"feature":15,"split":6}},
{"patternid":10,"pattern":{"id":0,"feature":4,"split":4}},
{"patternid":11,"pattern":{"id":0,"feature":9,"split":3}},
{"patternid":12,"pattern":{"id":0,"feature":11,"split":5}},
{"patternid":13,"pattern":{"id":0,"feature":12,"split":7}},
{"patternid":14,"pattern":{"id":0,"feature":8,"split":9}},
{"patternid":15,"pattern":{"id":0,"feature":9,"split":2}},
{"patternid":16,"pattern":{"id":0,"feature":15,"split":7}},
{"patternid":17,"pattern":{"id":0,"feature":5,"split":6}},
{"patternid":18,"pattern":{"id":0,"feature":9,"split":11}},
{"patternid":19,"pattern":{"id":0,"feature":9,"split":7}},
{"patternid":20,"pattern":{"id":0,"feature":2,"split":5}},
{"patternid":21,"pattern":{"id":0,"feature":0,"split":3}},
{"patternid":22,"pattern":{"id":0,"feature":7,"split":7}},
{"patternid":23,"pattern":{"id":0,"feature":6,"split":4}},
{"patternid":24,"pattern":{"id":0,"feature":9,"split":9}},
{"patternid":25,"pattern":{"id":0,"feature":13,"split":10}},
{"patternid":26,"pattern":{"id":0,"feature":12,"split":6}},
{"patternid":27,"pattern":{"id":0,"feature":10,"split":8}},
{"patternid":28,"pattern":{"id":0,"feature":10,"split":3}},
{"patternid":29,"pattern":{"id":0,"feature":6,"split":5}},
{"patternid":30,"pattern":{"id":0,"feature":5,"split":7}},
{"patternid":31,"pattern":{"id":0,"feature":6,"split":3}},
{"patternid":32,"pattern":{"id":0,"feature":1,"split":11}},
{"patternid":33,"pattern":{"id":0,"feature":14,"split":1}},
{"patternid":34,"pattern":{"id":0,"feature":5,"split":9}},
{"patternid":35,"pattern":{"id":0,"feature":13,"split":6}},
{"patternid":36,"pattern":{"id":0,"feature":3,"split":8}},
{"patternid":37,"pattern":{"id":0,"feature":0,"split":4}},
{"patternid":38,"pattern":{"id":0,"feature":12,"split":4}},
{"patternid":39,"pattern":{"id":0,"feature":9,"split":4}},
{"patternid":40,"pattern":{"id":0,"feature":9,"split":5}},
{"patternid":41,"pattern":{"id":0,"feature":11,"split":10}},
{"patternid":42,"pattern":{"id":0,"feature":5,"split":5}},
{"patternid":43,"pattern":{"id":0,"feature":14,"split":4}},
{"patternid":44,"pattern":{"id":0,"feature":2,"split":7}},
{"patternid":45,"pattern":{"id":0,"feature":11,"split":9}},
{"patternid":46,"pattern":{"id":0,"feature":6,"split":7}},
{"patternid":47,"pattern":{"id":0,"feature":15,"split":5}},
{"patternid":48,"pattern":{"id":0,"feature":12,"split":2}},
{"patternid":49,"pattern":{"id":0,"feature":11,"split":7}},
{"patternid":50,"pattern":{"id":0,"feature":10,"split":5}},
{"patternid":51,"pattern":{"id":0,"feature":12,"split":3}},
{"patternid":52,"pattern":{"id":0,"feature":10,"split":6}},
{"patternid":53,"pattern":{"id":0,"feature":13,"split":7}},
{"patternid":54,"pattern":{"id":0,"feature":9,"split":10}},
{"patternid":55,"pattern":{"id":0,"feature":8,"split":2}},
{"patternid":56,"pattern":{"id":0,"feature":7,"split":1}},
{"patternid":57,"pattern":{"id":0,"feature":7,"split":4}},
{"patternid":58,"pattern":{"id":0,"feature":8,"split":4}},
{"patternid":59,"pattern":{"id":0,"feature":13,"split":9}},
{"patternid":60,"pattern":{"id":0,"feature":12,"split":0}},
{"patternid":61,"pattern":{"id":0,"feature":5,"split":3}},
{"patternid":62,"pattern":{"id":0,"feature":9,"split":12}},
{"patternid":63,"pattern":{"id":0,"feature":8,"split":7}},
{"patternid":64,"pattern":{"id":0,"feature":11,"split":4}},
{"patternid":65,"pattern":{"id":0,"feature":6,"split":8}},
{"patternid":66,"pattern":{"id":0,"feature":7,"split":3}},
{"patternid":67,"pattern":{"id":0,"feature":11,"split":8}},
{"patternid":68,"pattern":{"id":0,"feature":14,"split":3}},
{"patternid":69,"pattern":{"id":0,"feature":11,"split":11}},
{"patternid":70,"pattern":{"id":0,"feature":15,"split":9}},
{"patternid":71,"pattern":{"id":0,"feature":14,"split":5}},
{"patternid":72,"pattern":{"id":0,"feature":6,"split":9}},
{"patternid":73,"pattern":{"id":0,"feature":10,"split":2}},
{"patternid":74,"pattern":{"id":0,"feature":8,"split":3}},
{"patternid":75,"pattern":{"id":0,"feature":12,"split":5}},
{"patternid":76,"pattern":{"id":0,"feature":14,"split":0}},
{"patternid":77,"pattern":{"id":0,"prediction":[]}},
{"patternid":78,"pattern":{"id":0,"feature":9,"split":8}},
{"patternid":79,"pattern":{"id":0,"feature":8,"split":5}},
{"patternid":80,"pattern":{"id":0,"feature":2,"split":3}},
{"patternid":81,"pattern":{"id":0,"feature":14,"split":2}},
{"patternid":82,"pattern":{"id":0,"feature":10,"split":7}},
{"patternid":83,"pattern":{"id":0,"feature":12,"split":1}},
{"patternid":84,"pattern":{"id":0,"feature":7,"split":5}},
{"patternid":85,"pattern":{"id":0,"feature":8,"split":8}},
{"patternid":86,"pattern":{"id":0,"feature":10,"split":9}},
{"patternid":87,"pattern":{"id":0,"feature":11,"split":6}},
{"patternid":88,"pattern":{"id":0,"feature":15,"split":8}},
{"patternid":89,"pattern":{"id":0,"feature":7,"split":6}},
{"patternid":90,"pattern":{"id":0,"feature":13,"split":8}},
{"patternid":91,"pattern":{"id":0,"feature":7,"split":2}},
{"patternid":92,"pattern":{"id":0,"feature":4,"split":3}},
{"patternid":93,"pattern":{"id":0,"feature":6,"split":10}},
{"patternid":180,"pattern":{"id":0,"feature":5,"split":6,"leftChild":{"id":1,"feature":5,"split":5}}},
{"patternid":179,"pattern":{"id":0,"feature":9,"split":11,"rightChild":{"id":1,"feature":14,"split":1}}},
{"patternid":178,"pattern":{"id":0,"feature":9,"split":11,"leftChild":{"id":1,"feature":10,"split":2}}},
{"patternid":177,"pattern":{"id":0,"feature":6,"split":4,"leftChild":{"id":1,"feature":12,"split":1}}},
{"patternid":176,"pattern":{"id":0,"feature":9,"split":9,"rightChild":{"id":1,"feature":0,"split":3}}},
{"patternid":175,"pattern":{"id":0,"feature":13,"split":10,"rightChild":{"id":1,"feature":6,"split":10}}},
{"patternid":174,"pattern":{"id":0,"feature":10,"split":8,"rightChild":{"id":1,"feature":12,"split":2}}},
{"patternid":173,"pattern":{"id":0,"feature":13,"split":6,"rightChild":{"id":1,"feature":14,"split":2}}},
{"patternid":172,"pattern":{"id":0,"feature":12,"split":4,"rightChild":{"id":1,"feature":8,"split":3}}},
{"patternid":171,"pattern":{"id":0,"feature":12,"split":4,"rightChild":{"id":1,"feature":9,"split":4}}},
{"patternid":170,"pattern":{"id":0,"feature":14,"split":4,"leftChild":{"id":1,"feature":12,"split":1}}},
{"patternid":169,"pattern":{"id":0,"feature":12,"split":2,"leftChild":{"id":1,"feature":7,"split":3}}},
{"patternid":168,"pattern":{"id":0,"feature":12,"split":2,"rightChild":{"id":1,"feature":5,"split":6}}},
{"patternid":167,"pattern":{"id":0,"feature":8,"split":4,"leftChild":{"id":1,"feature":12,"split":4}}},
{"patternid":166,"pattern":{"id":0,"feature":8,"split":4,"leftChild":{"id":1,"feature":13,"split":9}}},
{"patternid":165,"pattern":{"id":0,"feature":13,"split":9,"leftChild":{"id":1,"feature":6,"split":4}}},
{"patternid":164,"pattern":{"id":0,"feature":13,"split":9,"rightChild":{"id":1,"feature":10,"split":9}}},
{"patternid":163,"pattern":{"id":0,"feature":8,"split":7,"leftChild":{"id":1,"feature":11,"split":4}}},
{"patternid":162,"pattern":{"id":0,"feature":8,"split":7,"rightChild":{"id":1,"feature":7,"split":5}}},
{"patternid":161,"pattern":{"id":0,"feature":11,"split":4,"leftChild":{"id":1,"feature":14,"split":2}}},
{"patternid":160,"pattern":{"id":0,"feature":11,"split":4,"leftChild":{"id":1,"feature":6,"split":8}}},
{"patternid":159,"pattern":{"id":0,"feature":11,"split":4,"rightChild":{"id":1,"feature":8,"split":4}}},
{"patternid":158,"pattern":{"id":0,"feature":11,"split":8,"rightChild":{"id":1,"feature":7,"split":4}}},
{"patternid":157,"pattern":{"id":0,"feature":6,"split":9,"rightChild":{"id":1,"feature":8,"split":4}}},
{"patternid":155,"pattern":{"id":0,"feature":6,"split":9,"rightChild":{"id":1,"feature":11,"split":4}}},
{"patternid":154,"pattern":{"id":0,"feature":6,"split":9,"rightChild":{"id":1,"feature":10,"split":9}}},
{"patternid":152,"pattern":{"id":0,"feature":6,"split":9,"rightChild":{"id":1,"feature":12,"split":5}}},
{"patternid":156,"pattern":{"id":0,"feature":6,"split":9,"leftChild":{"id":1,"feature":13,"split":7}}},
{"patternid":153,"pattern":{"id":0,"feature":6,"split":9,"leftChild":{"id":1,"feature":10,"split":2}}},
{"patternid":151,"pattern":{"id":0,"feature":6,"split":9,"leftChild":{"id":1,"feature":12,"split":1}}},
{"patternid":150,"pattern":{"id":0,"feature":10,"split":2,"leftChild":{"id":1,"feature":7,"split":3}}},
{"patternid":149,"pattern":{"id":0,"feature":10,"split":2,"leftChild":{"id":1,"feature":9,"split":3}}},
{"patternid":148,"pattern":{"id":0,"feature":10,"split":2,"leftChild":{"id":1,"feature":5,"split":6}}},
{"patternid":147,"pattern":{"id":0,"feature":10,"split":2,"leftChild":{"id":1,"feature":12,"split":1}}},
{"patternid":146,"pattern":{"id":0,"feature":10,"split":2,"rightChild":{"id":1,"feature":12,"split":0}}},
{"patternid":145,"pattern":{"id":0,"feature":10,"split":2,"rightChild":{"id":1,"feature":15,"split":8}}},
{"patternid":144,"pattern":{"id":0,"feature":10,"split":2,"rightChild":{"id":1,"feature":14,"split":2}}},
{"patternid":142,"pattern":{"id":0,"feature":8,"split":3,"rightChild":{"id":1,"feature":9,"split":4}}},
{"patternid":143,"pattern":{"id":0,"feature":8,"split":3,"leftChild":{"id":1,"feature":14,"split":4}}},
{"patternid":141,"pattern":{"id":0,"feature":8,"split":3,"leftChild":{"id":1,"feature":12,"split":5}}},
{"patternid":140,"pattern":{"id":0,"feature":14,"split":2,"leftChild":{"id":1,"feature":9,"split":10}}},
{"patternid":139,"pattern":{"id":0,"feature":14,"split":2,"leftChild":{"id":1,"feature":6,"split":9}}},
{"patternid":138,"pattern":{"id":0,"feature":14,"split":2,"rightChild":{"id":1,"feature":8,"split":7}}},
{"patternid":137,"pattern":{"id":0,"feature":10,"split":7,"rightChild":{"id":1,"feature":8,"split":3}}},
{"patternid":136,"pattern":{"id":0,"feature":12,"split":1,"rightChild":{"id":1,"feature":0,"split":4}}},
{"patternid":135,"pattern":{"id":0,"feature":12,"split":1,"rightChild":{"id":1,"feature":12,"split":6}}},
{"patternid":134,"pattern":{"id":0,"feature":12,"split":1,"rightChild":{"id":1,"feature":14,"split":2}}},
{"patternid":133,"pattern":{"id":0,"feature":10,"split":9,"rightChild":{"id":1,"feature":13,"split":8}}},
{"patternid":132,"pattern":{"id":0,"feature":10,"split":9,"leftChild":{"id":1,"feature":12,"split":4}}},
{"patternid":131,"pattern":{"id":0,"feature":15,"split":8,"rightChild":{"id":1,"feature":12,"split":2}}},
{"patternid":130,"pattern":{"id":0,"feature":6,"split":10,"leftChild":{"id":1,"feature":7,"split":2}}},
{"patternid":184,"pattern":{"id":0,"feature":14,"split":2,"rightChild":{"id":1,"feature":8,"split":7,"leftChild":{"id":2,"feature":11,"split":4}}}},
{"patternid":183,"pattern":{"id":0,"feature":6,"split":9,"rightChild":{"id":1,"feature":10,"split":9,"rightChild":{"id":2,"feature":13,"split":8}}}},
{"patternid":182,"pattern":{"id":0,"feature":8,"split":4,"leftChild":{"id":1,"feature":12,"split":4,"rightChild":{"id":2,"feature":8,"split":3}}}},
{"patternid":181,"pattern":{"id":0,"feature":10,"split":8,"rightChild":{"id":1,"feature":12,"split":2,"leftChild":{"id":2,"feature":7,"split":3}}}}]