[{"patternid":1,"pattern":{"id":0,"feature":4,"split":0.03849999979138374,"leftChild":{"id":1,"feature":7,"split":0.991629958152771,"leftChild":{"id":2,"feature":1,"split":0.5249999761581421,"leftChild":{"id":3,"feature":3,"split":1.225000023841858,"leftChild":{"id":4,"feature":5,"split":10.5,"leftChild":{"id":5,"prediction":[]},"rightChild":{"id":6,"prediction":[]}},"rightChild":{"id":7,"feature":8,"split":3.0749998092651367,"leftChild":{"id":8,"prediction":[]},"rightChild":{"id":9,"prediction":[]}}},"rightChild":{"id":10,"feature":5,"split":25.0,"leftChild":{"id":11,"feature":4,"split":0.030499998480081558,"leftChild":{"id":12,"prediction":[]},"rightChild":{"id":13,"prediction":[]}},"rightChild":{"id":14,"feature":10,"split":12.549999237060547,"leftChild":{"id":15,"prediction":[]},"rightChild":{"id":16,"prediction":[]}}}},"rightChild":{"id":17,"feature":5,"split":16.5,"leftChild":{"id":18,"feature":3,"split":2.049999952316284,"leftChild":{"id":19,"feature":7,"split":0.9938000440597534,"leftChild":{"id":20,"prediction":[]},"rightChild":{"id":21,"prediction":[]}},"rightChild":{"id":22,"feature":5,"split":11.5,"leftChild":{"id":23,"prediction":[]},"rightChild":{"id":24,"prediction":[]}}},"rightChild":{"id":25,"feature":9,"split":0.3449999988079071,"leftChild":{"id":26,"feature":8,"split":3.3399999141693115,"leftChild":{"id":27,"prediction":[]},"rightChild":{"id":28,"prediction":[]}},"rightChild":{"id":29,"feature":6,"split":182.5,"leftChild":{"id":30,"prediction":[]},"rightChild":{"id":31,"prediction":[]}}}}},"rightChild":{"id":32,"feature":1,"split":0.22499999403953552,"leftChild":{"id":33,"feature":8,"split":2.9749999046325684,"leftChild":{"id":34,"feature":10,"split":9.149999618530273,"leftChild":{"id":35,"feature":6,"split":179.5,"leftChild":{"id":36,"prediction":[]},"rightChild":{"id":37,"prediction":[]}},"rightChild":{"id":38,"feature":3,"split":8.399999618530273,"leftChild":{"id":39,"prediction":[]},"rightChild":{"id":40,"prediction":[]}}},"rightChild":{"id":41,"feature":3,"split":5.525000095367432,"leftChild":{"id":42,"feature":10,"split":10.850000381469727,"leftChild":{"id":43,"prediction":[]},"rightChild":{"id":44,"prediction":[]}},"rightChild":{"id":45,"feature":0,"split":7.25,"leftChild":{"id":46,"prediction":[]},"rightChild":{"id":47,"prediction":[]}}}},"rightChild":{"id":48,"feature":0,"split":10.050000190734863,"leftChild":{"id":49,"feature":10,"split":10.725000381469727,"leftChild":{"id":50,"feature":2,"split":0.5450000166893005,"leftChild":{"id":51,"prediction":[]},"rightChild":{"id":52,"prediction":[]}},"rightChild":{"id":53,"feature":1,"split":0.4950000047683716,"leftChild":{"id":54,"prediction":[]},"rightChild":{"id":55,"prediction":[]}}},"rightChild":{"id":56,"feature":9,"split":0.6449999809265137,"leftChild":{"id":57,"feature":8,"split":3.2750000953674316,"leftChild":{"id":58,"prediction":[]},"rightChild":{"id":59,"prediction":[]}},"rightChild":{"id":60,"feature":8,"split":3.125,"leftChild":{"id":61,"prediction":[]},"rightChild":{"id":62,"prediction":[]}}}}}}},
{"patternid":2,"pattern":{"id":0,"feature":4,"split":0.03849999979138374,"leftChild":{"id":1,"feature":7,"split":0.991629958152771,"leftChild":{"id":2,"feature":1,"split":0.5249999761581421,"leftChild":{"id":3,"feature":3,"split":1.225000023841858,"leftChild":{"id":4,"feature":5,"split":10.5,"leftChild":{"id":5,"prediction":[]},"rightChild":{"id":6,"prediction":[]}},"rightChild":{"id":7,"feature":8,"split":3.0749998092651367,"leftChild":{"id":8,"prediction":[]},"rightChild":{"id":9,"prediction":[]}}},"rightChild":{"id":10,"feature":5,"split":25.0,"leftChild":{"id":11,"feature":4,"split":0.030499998480081558,"leftChild":{"id":12,"prediction":[]},"rightChild":{"id":13,"prediction":[]}},"rightChild":{"id":14,"feature":10,"split":12.549999237060547,"leftChild":{"id":15,"prediction":[]},"rightChild":{"id":16,"prediction":[]}}}},"rightChild":{"id":17,"feature":5,"split":16.5,"leftChild":{"id":18,"feature":3,"split":2.049999952316284,"leftChild":{"id":19,"feature":7,"split":0.9938000440597534,"leftChild":{"id":20,"prediction":[]},"rightChild":{"id":21,"prediction":[]}},"rightChild":{"id":22,"feature":5,"split":11.5,"leftChild":{"id":23,"prediction":[]},"rightChild":{"id":24,"prediction":[]}}},"rightChild":{"id":25,"feature":9,"split":0.3449999988079071,"leftChild":{"id":26,"feature":8,"split":3.3399999141693115,"leftChild":{"id":27,"prediction":[]},"rightChild":{"id":28,"prediction":[]}},"rightChild":{"id":29,"feature":6,"split":182.5,"leftChild":{"id":30,"prediction":[]},"rightChild":{"id":31,"prediction":[]}}}}},"rightChild":{"id":32,"feature":1,"split":0.22499999403953552,"leftChild":{"id":33,"feature":8,"split":2.9749999046325684,"leftChild":{"id":34,"feature":10,"split":9.149999618530273,"leftChild":{"id":35,"feature":6,"split":179.5,"leftChild":{"id":36,"prediction":[]},"rightChild":{"id":37,"prediction":[]}},"rightChild":{"id":38,"feature":3,"split":8.399999618530273,"leftChild":{"id":39,"prediction":[]},"rightChild":{"id":40,"prediction":[]}}},"rightChild":{"id":41,"feature":3,"split":5.525000095367432,"leftChild":{"id":42,"feature":10,"split":10.850000381469727,"leftChild":{"id":43,"prediction":[]},"rightChild":{"id":44,"prediction":[]}},"rightChild":{"id":45,"feature":0,"split":7.25,"leftChild":{"id":46,"prediction":[]},"rightChild":{"id":47,"prediction":[]}}}},"rightChild":{"id":48,"feature":0,"split":10.050000190734863,"leftChild":{"id":49,"feature":10,"split":10.725000381469727,"leftChild":{"id":50,"feature":2,"split":0.5450000166893005,"leftChild":{"id":51,"prediction":[]},"rightChild":{"id":52,"prediction":[]}},"rightChild":{"id":53,"feature":1,"split":0.4950000047683716,"leftChild":{"id":54,"prediction":[]},"rightChild":{"id":55,"prediction":[]}}},"rightChild":{"id":56,"feature":9,"split":0.6449999809265137,"leftChild":{"id":57,"feature":8,"split":3.2750000953674316,"leftChild":{"id":58,"prediction":[]},"rightChild":{"id":59,"prediction":[]}},"rightChild":{"id":60,"feature":8,"split":3.125,"leftChild":{"id":61,"prediction":[]},"rightChild":{"id":62,"prediction":[]}}}}}}},
{"patternid":3,"pattern":{"id":0,"feature":4,"split":0.03849999979138374,"leftChild":{"id":1,"feature":7,"split":0.991629958152771,"leftChild":{"id":2,"feature":1,"split":0.5249999761581421,"leftChild":{"id":3,"feature":3,"split":1.225000023841858,"leftChild":{"id":4,"feature":5,"split":10.5,"leftChild":{"id":5,"prediction":[]},"rightChild":{"id":6,"prediction":[]}},"rightChild":{"id":7,"feature":8,"split":3.0749998092651367,"leftChild":{"id":8,"prediction":[]},"rightChild":{"id":9,"prediction":[]}}},"rightChild":{"id":10,"feature":5,"split":25.0,"leftChild":{"id":11,"feature":4,"split":0.030499998480081558,"leftChild":{"id":12,"prediction":[]},"rightChild":{"id":13,"prediction":[]}},"rightChild":{"id":14,"feature":10,"split":12.549999237060547,"leftChild":{"id":15,"prediction":[]},"rightChild":{"id":16,"prediction":[]}}}},"rightChild":{"id":17,"feature":5,"split":16.5,"leftChild":{"id":18,"feature":3,"split":2.049999952316284,"leftChild":{"id":19,"feature":7,"split":0.9938000440597534,"leftChild":{"id":20,"prediction":[]},"rightChild":{"id":21,"prediction":[]}},"rightChild":{"id":22,"feature":5,"split":11.5,"leftChild":{"id":23,"prediction":[]},"rightChild":{"id":24,"prediction":[]}}},"rightChild":{"id":25,"feature":9,"split":0.3449999988079071,"leftChild":{"id":26,"feature":8,"split":3.3399999141693115,"leftChild":{"id":27,"prediction":[]},"rightChild":{"id":28,"prediction":[]}},"rightChild":{"id":29,"feature":6,"split":182.5,"leftChild":{"id":30,"prediction":[]},"rightChild":{"id":31,"prediction":[]}}}}},"rightChild":{"id":32,"feature":1,"split":0.22499999403953552,"leftChild":{"id":33,"feature":8,"split":2.9749999046325684,"leftChild":{"id":34,"feature":10,"split":9.149999618530273,"leftChild":{"id":35,"feature":6,"split":179.5,"leftChild":{"id":36,"prediction":[]},"rightChild":{"id":37,"prediction":[]}},"rightChild":{"id":38,"feature":3,"split":8.399999618530273,"leftChild":{"id":39,"prediction":[]},"rightChild":{"id":40,"prediction":[]}}},"rightChild":{"id":41,"feature":3,"split":5.525000095367432,"leftChild":{"id":42,"feature":10,"split":10.850000381469727,"leftChild":{"id":43,"prediction":[]},"rightChild":{"id":44,"prediction":[]}},"rightChild":{"id":45,"feature":0,"split":7.25,"leftChild":{"id":46,"prediction":[]},"rightChild":{"id":47,"prediction":[]}}}},"rightChild":{"id":48,"feature":0,"split":10.050000190734863,"leftChild":{"id":49,"feature":10,"split":10.725000381469727,"leftChild":{"id":50,"feature":2,"split":0.5450000166893005,"leftChild":{"id":51,"prediction":[]},"rightChild":{"id":52,"prediction":[]}},"rightChild":{"id":53,"feature":1,"split":0.4950000047683716,"leftChild":{"id":54,"prediction":[]},"rightChild":{"id":55,"prediction":[]}}},"rightChild":{"id":56,"feature":9,"split":0.6449999809265137,"leftChild":{"id":57,"feature":8,"split":3.2750000953674316,"leftChild":{"id":58,"prediction":[]},"rightChild":{"id":59,"prediction":[]}},"rightChild":{"id":60,"feature":8,"split":3.125,"leftChild":{"id":61,"prediction":[]},"rightChild":{"id":62,"prediction":[]}}}}}}},
{"patternid":4,"pattern":{"id":0,"feature":4,"split":0.03849999979138374,"leftChild":{"id":1,"feature":7,"split":0.991629958152771,"leftChild":{"id":2,"feature":1,"split":0.5249999761581421,"leftChild":{"id":3,"feature":3,"split":1.225000023841858,"leftChild":{"id":4,"feature":5,"split":10.5,"leftChild":{"id":5,"prediction":[]},"rightChild":{"id":6,"prediction":[]}},"rightChild":{"id":7,"feature":8,"split":3.0749998092651367,"leftChild":{"id":8,"prediction":[]},"rightChild":{"id":9,"prediction":[]}}},"rightChild":{"id":10,"feature":5,"split":25.0,"leftChild":{"id":11,"feature":4,"split":0.030499998480081558,"leftChild":{"id":12,"prediction":[]},"rightChild":{"id":13,"prediction":[]}},"rightChild":{"id":14,"feature":10,"split":12.549999237060547,"leftChild":{"id":15,"prediction":[]},"rightChild":{"id":16,"prediction":[]}}}},"rightChild":{"id":17,"feature":5,"split":16.5,"leftChild":{"id":18,"feature":3,"split":2.049999952316284,"leftChild":{"id":19,"feature":7,"split":0.9938000440597534,"leftChild":{"id":20,"prediction":[]},"rightChild":{"id":21,"prediction":[]}},"rightChild":{"id":22,"feature":5,"split":11.5,"leftChild":{"id":23,"prediction":[]},"rightChild":{"id":24,"prediction":[]}}},"rightChild":{"id":25,"feature":9,"split":0.3449999988079071,"leftChild":{"id":26,"feature":8,"split":3.3399999141693115,"leftChild":{"id":27,"prediction":[]},"rightChild":{"id":28,"prediction":[]}},"rightChild":{"id":29,"feature":6,"split":182.5,"leftChild":{"id":30,"prediction":[]},"rightChild":{"id":31,"prediction":[]}}}}},"rightChild":{"id":32,"feature":1,"split":0.22499999403953552,"leftChild":{"id":33,"feature":8,"split":2.9749999046325684,"leftChild":{"id":34,"feature":10,"split":9.149999618530273,"leftChild":{"id":35,"feature":6,"split":179.5,"leftChild":{"id":36,"prediction":[]},"rightChild":{"id":37,"prediction":[]}},"rightChild":{"id":38,"feature":3,"split":8.399999618530273,"leftChild":{"id":39,"prediction":[]},"rightChild":{"id":40,"prediction":[]}}},"rightChild":{"id":41,"feature":3,"split":5.525000095367432,"leftChild":{"id":42,"feature":10,"split":10.850000381469727,"leftChild":{"id":43,"prediction":[]},"rightChild":{"id":44,"prediction":[]}},"rightChild":{"id":45,"feature":0,"split":7.25,"leftChild":{"id":46,"prediction":[]},"rightChild":{"id":47,"prediction":[]}}}},"rightChild":{"id":48,"feature":0,"split":10.050000190734863,"leftChild":{"id":49,"feature":10,"split":10.725000381469727,"leftChild":{"id":50,"feature":2,"split":0.5450000166893005,"leftChild":{"id":51,"prediction":[]},"rightChild":{"id":52,"prediction":[]}},"rightChild":{"id":53,"feature":1,"split":0.4950000047683716,"leftChild":{"id":54,"prediction":[]},"rightChild":{"id":55,"prediction":[]}}},"rightChild":{"id":56,"feature":9,"split":0.6449999809265137,"leftChild":{"id":57,"feature":8,"split":3.2750000953674316,"leftChild":{"id":58,"prediction":[]},"rightChild":{"id":59,"prediction":[]}},"rightChild":{"id":60,"feature":8,"split":3.125,"leftChild":{"id":61,"prediction":[]},"rightChild":{"id":62,"prediction":[]}}}}}}},
{"patternid":5,"pattern":{"id":0,"feature":4,"split":0.03849999979138374,"leftChild":{"id":1,"feature":7,"split":0.991629958152771,"leftChild":{"id":2,"feature":1,"split":0.5249999761581421,"leftChild":{"id":3,"feature":3,"split":1.225000023841858,"leftChild":{"id":4,"feature":5,"split":10.5,"leftChild":{"id":5,"prediction":[]},"rightChild":{"id":6,"prediction":[]}},"rightChild":{"id":7,"feature":8,"split":3.0749998092651367,"leftChild":{"id":8,"prediction":[]},"rightChild":{"id":9,"prediction":[]}}},"rightChild":{"id":10,"feature":5,"split":25.0,"leftChild":{"id":11,"feature":4,"split":0.030499998480081558,"leftChild":{"id":12,"prediction":[]},"rightChild":{"id":13,"prediction":[]}},"rightChild":{"id":14,"feature":10,"split":12.549999237060547,"leftChild":{"id":15,"prediction":[]},"rightChild":{"id":16,"prediction":[]}}}},"rightChild":{"id":17,"feature":5,"split":16.5,"leftChild":{"id":18,"feature":3,"split":2.049999952316284,"leftChild":{"id":19,"feature":7,"split":0.9938000440597534,"leftChild":{"id":20,"prediction":[]},"rightChild":{"id":21,"prediction":[]}},"rightChild":{"id":22,"feature":5,"split":11.5,"leftChild":{"id":23,"prediction":[]},"rightChild":{"id":24,"prediction":[]}}},"rightChild":{"id":25,"feature":9,"split":0.3449999988079071,"leftChild":{"id":26,"feature":8,"split":3.3399999141693115,"leftChild":{"id":27,"prediction":[]},"rightChild":{"id":28,"prediction":[]}},"rightChild":{"id":29,"feature":6,"split":182.5,"leftChild":{"id":30,"prediction":[]},"rightChild":{"id":31,"prediction":[]}}}}},"rightChild":{"id":32,"feature":1,"split":0.22499999403953552,"leftChild":{"id":33,"feature":8,"split":2.9749999046325684,"leftChild":{"id":34,"feature":10,"split":9.149999618530273,"leftChild":{"id":35,"feature":6,"split":179.5,"leftChild":{"id":36,"prediction":[]},"rightChild":{"id":37,"prediction":[]}},"rightChild":{"id":38,"feature":3,"split":8.399999618530273,"leftChild":{"id":39,"prediction":[]},"rightChild":{"id":40,"prediction":[]}}},"rightChild":{"id":41,"feature":3,"split":5.525000095367432,"leftChild":{"id":42,"feature":10,"split":10.850000381469727,"leftChild":{"id":43,"prediction":[]},"rightChild":{"id":44,"prediction":[]}},"rightChild":{"id":45,"feature":0,"split":7.25,"leftChild":{"id":46,"prediction":[]},"rightChild":{"id":47,"prediction":[]}}}},"rightChild":{"id":48,"feature":0,"split":10.050000190734863,"leftChild":{"id":49,"feature":10,"split":10.725000381469727,"leftChild":{"id":50,"feature":2,"split":0.5450000166893005,"leftChild":{"id":51,"prediction":[]},"rightChild":{"id":52,"prediction":[]}},"rightChild":{"id":53,"feature":1,"split":0.4950000047683716,"leftChild":{"id":54,"prediction":[]},"rightChild":{"id":55,"prediction":[]}}},"rightChild":{"id":56,"feature":9,"split":0.6449999809265137,"leftChild":{"id":57,"feature":8,"split":3.2750000953674316,"leftChild":{"id":58,"prediction":[]},"rightChild":{"id":59,"prediction":[]}},"rightChild":{"id":60,"feature":8,"split":3.125,"leftChild":{"id":61,"prediction":[]},"rightChild":{"id":62,"prediction":[]}}}}}}},
{"patternid":6,"pattern":{"id":0,"feature":4,"split":0.03849999979138374,"leftChild":{"id":1,"feature":7,"split":0.991629958152771,"leftChild":{"id":2,"feature":1,"split":0.5249999761581421,"leftChild":{"id":3,"feature":3,"split":1.225000023841858,"leftChild":{"id":4,"feature":5,"split":10.5,"leftChild":{"id":5,"prediction":[]},"rightChild":{"id":6,"prediction":[]}},"rightChild":{"id":7,"feature":8,"split":3.0749998092651367,"leftChild":{"id":8,"prediction":[]},"rightChild":{"id":9,"prediction":[]}}},"rightChild":{"id":10,"feature":5,"split":25.0,"leftChild":{"id":11,"feature":4,"split":0.030499998480081558,"leftChild":{"id":12,"prediction":[]},"rightChild":{"id":13,"prediction":[]}},"rightChild":{"id":14,"feature":10,"split":12.549999237060547,"leftChild":{"id":15,"prediction":[]},"rightChild":{"id":16,"prediction":[]}}}},"rightChild":{"id":17,"feature":5,"split":16.5,"leftChild":{"id":18,"feature":3,"split":2.049999952316284,"leftChild":{"id":19,"feature":7,"split":0.9938000440597534,"leftChild":{"id":20,"prediction":[]},"rightChild":{"id":21,"prediction":[]}},"rightChild":{"id":22,"feature":5,"split":11.5,"leftChild":{"id":23,"prediction":[]},"rightChild":{"id":24,"prediction":[]}}},"rightChild":{"id":25,"feature":9,"split":0.3449999988079071,"leftChild":{"id":26,"feature":8,"split":3.3399999141693115,"leftChild":{"id":27,"prediction":[]},"rightChild":{"id":28,"prediction":[]}},"rightChild":{"id":29,"feature":6,"split":182.5,"leftChild":{"id":30,"prediction":[]},"rightChild":{"id":31,"prediction":[]}}}}},"rightChild":{"id":32,"feature":1,"split":0.22499999403953552,"leftChild":{"id":33,"feature":8,"split":2.9749999046325684,"leftChild":{"id":34,"feature":10,"split":9.149999618530273,"leftChild":{"id":35,"feature":6,"split":179.5,"leftChild":{"id":36,"prediction":[]},"rightChild":{"id":37,"prediction":[]}},"rightChild":{"id":38,"feature":3,"split":8.399999618530273,"leftChild":{"id":39,"prediction":[]},"rightChild":{"id":40,"prediction":[]}}},"rightChild":{"id":41,"feature":3,"split":5.525000095367432,"leftChild":{"id":42,"feature":10,"split":10.850000381469727,"leftChild":{"id":43,"prediction":[]},"rightChild":{"id":44,"prediction":[]}},"rightChild":{"id":45,"feature":0,"split":7.25,"leftChild":{"id":46,"prediction":[]},"rightChild":{"id":47,"prediction":[]}}}},"rightChild":{"id":48,"feature":0,"split":10.050000190734863,"leftChild":{"id":49,"feature":10,"split":10.725000381469727,"leftChild":{"id":50,"feature":2,"split":0.5450000166893005,"leftChild":{"id":51,"prediction":[]},"rightChild":{"id":52,"prediction":[]}},"rightChild":{"id":53,"feature":1,"split":0.4950000047683716,"leftChild":{"id":54,"prediction":[]},"rightChild":{"id":55,"prediction":[]}}},"rightChild":{"id":56,"feature":9,"split":0.6449999809265137,"leftChild":{"id":57,"feature":8,"split":3.2750000953674316,"leftChild":{"id":58,"prediction":[]},"rightChild":{"id":59,"prediction":[]}},"rightChild":{"id":60,"feature":8,"split":3.125,"leftChild":{"id":61,"prediction":[]},"rightChild":{"id":62,"prediction":[]}}}}}}},
{"patternid":7,"pattern":{"id":0,"feature":4,"split":0.03849999979138374,"leftChild":{"id":1,"feature":7,"split":0.991629958152771,"leftChild":{"id":2,"feature":1,"split":0.5249999761581421,"leftChild":{"id":3,"feature":3,"split":1.225000023841858,"leftChild":{"id":4,"feature":5,"split":10.5,"leftChild":{"id":5,"prediction":[]},"rightChild":{"id":6,"prediction":[]}},"rightChild":{"id":7,"feature":8,"split":3.0749998092651367,"leftChild":{"id":8,"prediction":[]},"rightChild":{"id":9,"prediction":[]}}},"rightChild":{"id":10,"feature":5,"split":25.0,"leftChild":{"id":11,"feature":4,"split":0.030499998480081558,"leftChild":{"id":12,"prediction":[]},"rightChild":{"id":13,"prediction":[]}},"rightChild":{"id":14,"feature":10,"split":12.549999237060547,"leftChild":{"id":15,"prediction":[]},"rightChild":{"id":16,"prediction":[]}}}},"rightChild":{"id":17,"feature":5,"split":16.5,"leftChild":{"id":18,"feature":3,"split":2.049999952316284,"leftChild":{"id":19,"feature":7,"split":0.9938000440597534,"leftChild":{"id":20,"prediction":[]},"rightChild":{"id":21,"prediction":[]}},"rightChild":{"id":22,"feature":5,"split":11.5,"leftChild":{"id":23,"prediction":[]},"rightChild":{"id":24,"prediction":[]}}},"rightChild":{"id":25,"feature":9,"split":0.3449999988079071,"leftChild":{"id":26,"feature":8,"split":3.3399999141693115,"leftChild":{"id":27,"prediction":[]},"rightChild":{"id":28,"prediction":[]}},"rightChild":{"id":29,"feature":6,"split":182.5,"leftChild":{"id":30,"prediction":[]},"rightChild":{"id":31,"prediction":[]}}}}},"rightChild":{"id":32,"feature":1,"split":0.22499999403953552,"leftChild":{"id":33,"feature":8,"split":2.9749999046325684,"leftChild":{"id":34,"feature":10,"split":9.149999618530273,"leftChild":{"id":35,"feature":6,"split":179.5,"leftChild":{"id":36,"prediction":[]},"rightChild":{"id":37,"prediction":[]}},"rightChild":{"id":38,"feature":3,"split":8.399999618530273,"leftChild":{"id":39,"prediction":[]},"rightChild":{"id":40,"prediction":[]}}},"rightChild":{"id":41,"feature":3,"split":5.525000095367432,"leftChild":{"id":42,"feature":10,"split":10.850000381469727,"leftChild":{"id":43,"prediction":[]},"rightChild":{"id":44,"prediction":[]}},"rightChild":{"id":45,"feature":0,"split":7.25,"leftChild":{"id":46,"prediction":[]},"rightChild":{"id":47,"prediction":[]}}}},"rightChild":{"id":48,"feature":0,"split":10.050000190734863,"leftChild":{"id":49,"feature":10,"split":10.725000381469727,"leftChild":{"id":50,"feature":2,"split":0.5450000166893005,"leftChild":{"id":51,"prediction":[]},"rightChild":{"id":52,"prediction":[]}},"rightChild":{"id":53,"feature":1,"split":0.4950000047683716,"leftChild":{"id":54,"prediction":[]},"rightChild":{"id":55,"prediction":[]}}},"rightChild":{"id":56,"feature":9,"split":0.6449999809265137,"leftChild":{"id":57,"feature":8,"split":3.2750000953674316,"leftChild":{"id":58,"prediction":[]},"rightChild":{"id":59,"prediction":[]}},"rightChild":{"id":60,"feature":8,"split":3.125,"leftChild":{"id":61,"prediction":[]},"rightChild":{"id":62,"prediction":[]}}}}}}},
{"patternid":8,"pattern":{"id":0,"feature":4,"split":0.03849999979138374,"leftChild":{"id":1,"feature":7,"split":0.991629958152771,"leftChild":{"id":2,"feature":1,"split":0.5249999761581421,"leftChild":{"id":3,"feature":3,"split":1.225000023841858,"leftChild":{"id":4,"feature":5,"split":10.5,"leftChild":{"id":5,"prediction":[]},"rightChild":{"id":6,"prediction":[]}},"rightChild":{"id":7,"feature":8,"split":3.0749998092651367,"leftChild":{"id":8,"prediction":[]},"rightChild":{"id":9,"prediction":[]}}},"rightChild":{"id":10,"feature":5,"split":25.0,"leftChild":{"id":11,"feature":4,"split":0.030499998480081558,"leftChild":{"id":12,"prediction":[]},"rightChild":{"id":13,"prediction":[]}},"rightChild":{"id":14,"feature":10,"split":12.549999237060547,"leftChild":{"id":15,"prediction":[]},"rightChild":{"id":16,"prediction":[]}}}},"rightChild":{"id":17,"feature":5,"split":16.5,"leftChild":{"id":18,"feature":3,"split":2.049999952316284,"leftChild":{"id":19,"feature":7,"split":0.9938000440597534,"leftChild":{"id":20,"prediction":[]},"rightChild":{"id":21,"prediction":[]}},"rightChild":{"id":22,"feature":5,"split":11.5,"leftChild":{"id":23,"prediction":[]},"rightChild":{"id":24,"prediction":[]}}},"rightChild":{"id":25,"feature":9,"split":0.3449999988079071,"leftChild":{"id":26,"feature":8,"split":3.3399999141693115,"leftChild":{"id":27,"prediction":[]},"rightChild":{"id":28,"prediction":[]}},"rightChild":{"id":29,"feature":6,"split":182.5,"leftChild":{"id":30,"prediction":[]},"rightChild":{"id":31,"prediction":[]}}}}},"rightChild":{"id":32,"feature":1,"split":0.22499999403953552,"leftChild":{"id":33,"feature":8,"split":2.9749999046325684,"leftChild":{"id":34,"feature":10,"split":9.149999618530273,"leftChild":{"id":35,"feature":6,"split":179.5,"leftChild":{"id":36,"prediction":[]},"rightChild":{"id":37,"prediction":[]}},"rightChild":{"id":38,"feature":3,"split":8.399999618530273,"leftChild":{"id":39,"prediction":[]},"rightChild":{"id":40,"prediction":[]}}},"rightChild":{"id":41,"feature":3,"split":5.525000095367432,"leftChild":{"id":42,"feature":10,"split":10.850000381469727,"leftChild":{"id":43,"prediction":[]},"rightChild":{"id":44,"prediction":[]}},"rightChild":{"id":45,"feature":0,"split":7.25,"leftChild":{"id":46,"prediction":[]},"rightChild":{"id":47,"prediction":[]}}}},"rightChild":{"id":48,"feature":0,"split":10.050000190734863,"leftChild":{"id":49,"feature":10,"split":10.725000381469727,"leftChild":{"id":50,"feature":2,"split":0.5450000166893005,"leftChild":{"id":51,"prediction":[]},"rightChild":{"id":52,"prediction":[]}},"rightChild":{"id":53,"feature":1,"split":0.4950000047683716,"leftChild":{"id":54,"prediction":[]},"rightChild":{"id":55,"prediction":[]}}},"rightChild":{"id":56,"feature":9,"split":0.6449999809265137,"leftChild":{"id":57,"feature":8,"split":3.2750000953674316,"leftChild":{"id":58,"prediction":[]},"rightChild":{"id":59,"prediction":[]}},"rightChild":{"id":60,"feature":8,"split":3.125,"leftChild":{"id":61,"prediction":[]},"rightChild":{"id":62,"prediction":[]}}}}}}},
{"patternid":9,"pattern":{"id":0,"feature":4,"split":0.03849999979138374,"leftChild":{"id":1,"feature":7,"split":0.991629958152771,"leftChild":{"id":2,"feature":1,"split":0.5249999761581421,"leftChild":{"id":3,"feature":3,"split":1.225000023841858,"leftChild":{"id":4,"feature":5,"split":10.5,"leftChild":{"id":5,"prediction":[]},"rightChild":{"id":6,"prediction":[]}},"rightChild":{"id":7,"feature":8,"split":3.0749998092651367,"leftChild":{"id":8,"prediction":[]},"rightChild":{"id":9,"prediction":[]}}},"rightChild":{"id":10,"feature":5,"split":25.0,"leftChild":{"id":11,"feature":4,"split":0.030499998480081558,"leftChild":{"id":12,"prediction":[]},"rightChild":{"id":13,"prediction":[]}},"rightChild":{"id":14,"feature":10,"split":12.549999237060547,"leftChild":{"id":15,"prediction":[]},"rightChild":{"id":16,"prediction":[]}}}},"rightChild":{"id":17,"feature":5,"split":16.5,"leftChild":{"id":18,"feature":3,"split":2.049999952316284,"leftChild":{"id":19,"feature":7,"split":0.9938000440597534,"leftChild":{"id":20,"prediction":[]},"rightChild":{"id":21,"prediction":[]}},"rightChild":{"id":22,"feature":5,"split":11.5,"leftChild":{"id":23,"prediction":[]},"rightChild":{"id":24,"prediction":[]}}},"rightChild":{"id":25,"feature":9,"split":0.3449999988079071,"leftChild":{"id":26,"feature":8,"split":3.3399999141693115,"leftChild":{"id":27,"prediction":[]},"rightChild":{"id":28,"prediction":[]}},"rightChild":{"id":29,"feature":6,"split":182.5,"leftChild":{"id":30,"prediction":[]},"rightChild":{"id":31,"prediction":[]}}}}},"rightChild":{"id":32,"feature":1,"split":0.22499999403953552,"leftChild":{"id":33,"feature":8,"split":2.9749999046325684,"leftChild":{"id":34,"feature":10,"split":9.149999618530273,"leftChild":{"id":35,"feature":6,"split":179.5,"leftChild":{"id":36,"prediction":[]},"rightChild":{"id":37,"prediction":[]}},"rightChild":{"id":38,"feature":3,"split":8.399999618530273,"leftChild":{"id":39,"prediction":[]},"rightChild":{"id":40,"prediction":[]}}},"rightChild":{"id":41,"feature":3,"split":5.525000095367432,"leftChild":{"id":42,"feature":10,"split":10.850000381469727,"leftChild":{"id":43,"prediction":[]},"rightChild":{"id":44,"prediction":[]}},"rightChild":{"id":45,"feature":0,"split":7.25,"leftChild":{"id":46,"prediction":[]},"rightChild":{"id":47,"prediction":[]}}}},"rightChild":{"id":48,"feature":0,"split":10.050000190734863,"leftChild":{"id":49,"feature":10,"split":10.725000381469727,"leftChild":{"id":50,"feature":2,"split":0.5450000166893005,"leftChild":{"id":51,"prediction":[]},"rightChild":{"id":52,"prediction":[]}},"rightChild":{"id":53,"feature":1,"split":0.4950000047683716,"leftChild":{"id":54,"prediction":[]},"rightChild":{"id":55,"prediction":[]}}},"rightChild":{"id":56,"feature":9,"split":0.6449999809265137,"leftChild":{"id":57,"feature":8,"split":3.2750000953674316,"leftChild":{"id":58,"prediction":[]},"rightChild":{"id":59,"prediction":[]}},"rightChild":{"id":60,"feature":8,"split":3.125,"leftChild":{"id":61,"prediction":[]},"rightChild":{"id":62,"prediction":[]}}}}}}},
{"patternid":10,"pattern":{"id":0,"feature":4,"split":0.03849999979138374,"leftChild":{"id":1,"feature":7,"split":0.991629958152771,"leftChild":{"id":2,"feature":1,"split":0.5249999761581421,"leftChild":{"id":3,"feature":3,"split":1.225000023841858,"leftChild":{"id":4,"feature":5,"split":10.5,"leftChild":{"id":5,"prediction":[]},"rightChild":{"id":6,"prediction":[]}},"rightChild":{"id":7,"feature":8,"split":3.0749998092651367,"leftChild":{"id":8,"prediction":[]},"rightChild":{"id":9,"prediction":[]}}},"rightChild":{"id":10,"feature":5,"split":25.0,"leftChild":{"id":11,"feature":4,"split":0.030499998480081558,"leftChild":{"id":12,"prediction":[]},"rightChild":{"id":13,"prediction":[]}},"rightChild":{"id":14,"feature":10,"split":12.549999237060547,"leftChild":{"id":15,"prediction":[]},"rightChild":{"id":16,"prediction":[]}}}},"rightChild":{"id":17,"feature":5,"split":16.5,"leftChild":{"id":18,"feature":3,"split":2.049999952316284,"leftChild":{"id":19,"feature":7,"split":0.9938000440597534,"leftChild":{"id":20,"prediction":[]},"rightChild":{"id":21,"prediction":[]}},"rightChild":{"id":22,"feature":5,"split":11.5,"leftChild":{"id":23,"prediction":[]},"rightChild":{"id":24,"prediction":[]}}},"rightChild":{"id":25,"feature":9,"split":0.3449999988079071,"leftChild":{"id":26,"feature":8,"split":3.3399999141693115,"leftChild":{"id":27,"prediction":[]},"rightChild":{"id":28,"prediction":[]}},"rightChild":{"id":29,"feature":6,"split":182.5,"leftChild":{"id":30,"prediction":[]},"rightChild":{"id":31,"prediction":[]}}}}},"rightChild":{"id":32,"feature":1,"split":0.22499999403953552,"leftChild":{"id":33,"feature":8,"split":2.9749999046325684,"leftChild":{"id":34,"feature":10,"split":9.149999618530273,"leftChild":{"id":35,"feature":6,"split":179.5,"leftChild":{"id":36,"prediction":[]},"rightChild":{"id":37,"prediction":[]}},"rightChild":{"id":38,"feature":3,"split":8.399999618530273,"leftChild":{"id":39,"prediction":[]},"rightChild":{"id":40,"prediction":[]}}},"rightChild":{"id":41,"feature":3,"split":5.525000095367432,"leftChild":{"id":42,"feature":10,"split":10.850000381469727,"leftChild":{"id":43,"prediction":[]},"rightChild":{"id":44,"prediction":[]}},"rightChild":{"id":45,"feature":0,"split":7.25,"leftChild":{"id":46,"prediction":[]},"rightChild":{"id":47,"prediction":[]}}}},"rightChild":{"id":48,"feature":0,"split":10.050000190734863,"leftChild":{"id":49,"feature":10,"split":10.725000381469727,"leftChild":{"id":50,"feature":2,"split":0.5450000166893005,"leftChild":{"id":51,"prediction":[]},"rightChild":{"id":52,"prediction":[]}},"rightChild":{"id":53,"feature":1,"split":0.4950000047683716,"leftChild":{"id":54,"prediction":[]},"rightChild":{"id":55,"prediction":[]}}},"rightChild":{"id":56,"feature":9,"split":0.6449999809265137,"leftChild":{"id":57,"feature":8,"split":3.2750000953674316,"leftChild":{"id":58,"prediction":[]},"rightChild":{"id":59,"prediction":[]}},"rightChild":{"id":60,"feature":8,"split":3.125,"leftChild":{"id":61,"prediction":[]},"rightChild":{"id":62,"prediction":[]}}}}}}},
{"patternid":11,"pattern":{"id":0,"feature":4,"split":0.03849999979138374,"leftChild":{"id":1,"feature":7,"split":0.991629958152771,"leftChild":{"id":2,"feature":1,"split":0.5249999761581421,"leftChild":{"id":3,"feature":3,"split":1.225000023841858,"leftChild":{"id":4,"feature":5,"split":10.5,"leftChild":{"id":5,"prediction":[]},"rightChild":{"id":6,"prediction":[]}},"rightChild":{"id":7,"feature":8,"split":3.0749998092651367,"leftChild":{"id":8,"prediction":[]},"rightChild":{"id":9,"prediction":[]}}},"rightChild":{"id":10,"feature":5,"split":25.0,"leftChild":{"id":11,"feature":4,"split":0.030499998480081558,"leftChild":{"id":12,"prediction":[]},"rightChild":{"id":13,"prediction":[]}},"rightChild":{"id":14,"feature":10,"split":12.549999237060547,"leftChild":{"id":15,"prediction":[]},"rightChild":{"id":16,"prediction":[]}}}},"rightChild":{"id":17,"feature":5,"split":16.5,"leftChild":{"id":18,"feature":3,"split":2.049999952316284,"leftChild":{"id":19,"feature":7,"split":0.9938000440597534,"leftChild":{"id":20,"prediction":[]},"rightChild":{"id":21,"prediction":[]}},"rightChild":{"id":22,"feature":5,"split":11.5,"leftChild":{"id":23,"prediction":[]},"rightChild":{"id":24,"prediction":[]}}},"rightChild":{"id":25,"feature":9,"split":0.3449999988079071,"leftChild":{"id":26,"feature":8,"split":3.3399999141693115,"leftChild":{"id":27,"prediction":[]},"rightChild":{"id":28,"prediction":[]}},"rightChild":{"id":29,"feature":6,"split":182.5,"leftChild":{"id":30,"prediction":[]},"rightChild":{"id":31,"prediction":[]}}}}},"rightChild":{"id":32,"feature":1,"split":0.22499999403953552,"leftChild":{"id":33,"feature":8,"split":2.9749999046325684,"leftChild":{"id":34,"feature":10,"split":9.149999618530273,"leftChild":{"id":35,"feature":6,"split":179.5,"leftChild":{"id":36,"prediction":[]},"rightChild":{"id":37,"prediction":[]}},"rightChild":{"id":38,"feature":3,"split":8.399999618530273,"leftChild":{"id":39,"prediction":[]},"rightChild":{"id":40,"prediction":[]}}},"rightChild":{"id":41,"feature":3,"split":5.525000095367432,"leftChild":{"id":42,"feature":10,"split":10.850000381469727,"leftChild":{"id":43,"prediction":[]},"rightChild":{"id":44,"prediction":[]}},"rightChild":{"id":45,"feature":0,"split":7.25,"leftChild":{"id":46,"prediction":[]},"rightChild":{"id":47,"prediction":[]}}}},"rightChild":{"id":48,"feature":0,"split":10.050000190734863,"leftChild":{"id":49,"feature":10,"split":10.725000381469727,"leftChild":{"id":50,"feature":2,"split":0.5450000166893005,"leftChild":{"id":51,"prediction":[]},"rightChild":{"id":52,"prediction":[]}},"rightChild":{"id":53,"feature":1,"split":0.4950000047683716,"leftChild":{"id":54,"prediction":[]},"rightChild":{"id":55,"prediction":[]}}},"rightChild":{"id":56,"feature":9,"split":0.6449999809265137,"leftChild":{"id":57,"feature":8,"split":3.2750000953674316,"leftChild":{"id":58,"prediction":[]},"rightChild":{"id":59,"prediction":[]}},"rightChild":{"id":60,"feature":8,"split":3.125,"leftChild":{"id":61,"prediction":[]},"rightChild":{"id":62,"prediction":[]}}}}}}},
{"patternid":12,"pattern":{"id":0,"feature":4,"split":0.03849999979138374,"leftChild":{"id":1,"feature":7,"split":0.991629958152771,"leftChild":{"id":2,"feature":1,"split":0.5249999761581421,"leftChild":{"id":3,"feature":3,"split":1.225000023841858,"leftChild":{"id":4,"feature":5,"split":10.5,"leftChild":{"id":5,"prediction":[]},"rightChild":{"id":6,"prediction":[]}},"rightChild":{"id":7,"feature":8,"split":3.0749998092651367,"leftChild":{"id":8,"prediction":[]},"rightChild":{"id":9,"prediction":[]}}},"rightChild":{"id":10,"feature":5,"split":25.0,"leftChild":{"id":11,"feature":4,"split":0.030499998480081558,"leftChild":{"id":12,"prediction":[]},"rightChild":{"id":13,"prediction":[]}},"rightChild":{"id":14,"feature":10,"split":12.549999237060547,"leftChild":{"id":15,"prediction":[]},"rightChild":{"id":16,"prediction":[]}}}},"rightChild":{"id":17,"feature":5,"split":16.5,"leftChild":{"id":18,"feature":3,"split":2.049999952316284,"leftChild":{"id":19,"feature":7,"split":0.9938000440597534,"leftChild":{"id":20,"prediction":[]},"rightChild":{"id":21,"prediction":[]}},"rightChild":{"id":22,"feature":5,"split":11.5,"leftChild":{"id":23,"prediction":[]},"rightChild":{"id":24,"prediction":[]}}},"rightChild":{"id":25,"feature":9,"split":0.3449999988079071,"leftChild":{"id":26,"feature":8,"split":3.3399999141693115,"leftChild":{"id":27,"prediction":[]},"rightChild":{"id":28,"prediction":[]}},"rightChild":{"id":29,"feature":6,"split":182.5,"leftChild":{"id":30,"prediction":[]},"rightChild":{"id":31,"prediction":[]}}}}},"rightChild":{"id":32,"feature":1,"split":0.22499999403953552,"leftChild":{"id":33,"feature":8,"split":2.9749999046325684,"leftChild":{"id":34,"feature":10,"split":9.149999618530273,"leftChild":{"id":35,"feature":6,"split":179.5,"leftChild":{"id":36,"prediction":[]},"rightChild":{"id":37,"prediction":[]}},"rightChild":{"id":38,"feature":3,"split":8.399999618530273,"leftChild":{"id":39,"prediction":[]},"rightChild":{"id":40,"prediction":[]}}},"rightChild":{"id":41,"feature":3,"split":5.525000095367432,"leftChild":{"id":42,"feature":10,"split":10.850000381469727,"leftChild":{"id":43,"prediction":[]},"rightChild":{"id":44,"prediction":[]}},"rightChild":{"id":45,"feature":0,"split":7.25,"leftChild":{"id":46,"prediction":[]},"rightChild":{"id":47,"prediction":[]}}}},"rightChild":{"id":48,"feature":0,"split":10.050000190734863,"leftChild":{"id":49,"feature":10,"split":10.725000381469727,"leftChild":{"id":50,"feature":2,"split":0.5450000166893005,"leftChild":{"id":51,"prediction":[]},"rightChild":{"id":52,"prediction":[]}},"rightChild":{"id":53,"feature":1,"split":0.4950000047683716,"leftChild":{"id":54,"prediction":[]},"rightChild":{"id":55,"prediction":[]}}},"rightChild":{"id":56,"feature":9,"split":0.6449999809265137,"leftChild":{"id":57,"feature":8,"split":3.2750000953674316,"leftChild":{"id":58,"prediction":[]},"rightChild":{"id":59,"prediction":[]}},"rightChild":{"id":60,"feature":8,"split":3.125,"leftChild":{"id":61,"prediction":[]},"rightChild":{"id":62,"prediction":[]}}}}}}},
{"patternid":13,"pattern":{"id":0,"feature":4,"split":0.03849999979138374,"leftChild":{"id":1,"feature":7,"split":0.991629958152771,"leftChild":{"id":2,"feature":1,"split":0.5249999761581421,"leftChild":{"id":3,"feature":3,"split":1.225000023841858,"leftChild":{"id":4,"feature":5,"split":10.5,"leftChild":{"id":5,"prediction":[]},"rightChild":{"id":6,"prediction":[]}},"rightChild":{"id":7,"feature":8,"split":3.0749998092651367,"leftChild":{"id":8,"prediction":[]},"rightChild":{"id":9,"prediction":[]}}},"rightChild":{"id":10,"feature":5,"split":25.0,"leftChild":{"id":11,"feature":4,"split":0.030499998480081558,"leftChild":{"id":12,"prediction":[]},"rightChild":{"id":13,"prediction":[]}},"rightChild":{"id":14,"feature":10,"split":12.549999237060547,"leftChild":{"id":15,"prediction":[]},"rightChild":{"id":16,"prediction":[]}}}},"rightChild":{"id":17,"feature":5,"split":16.5,"leftChild":{"id":18,"feature":3,"split":2.049999952316284,"leftChild":{"id":19,"feature":7,"split":0.9938000440597534,"leftChild":{"id":20,"prediction":[]},"rightChild":{"id":21,"prediction":[]}},"rightChild":{"id":22,"feature":5,"split":11.5,"leftChild":{"id":23,"prediction":[]},"rightChild":{"id":24,"prediction":[]}}},"rightChild":{"id":25,"feature":9,"split":0.3449999988079071,"leftChild":{"id":26,"feature":8,"split":3.3399999141693115,"leftChild":{"id":27,"prediction":[]},"rightChild":{"id":28,"prediction":[]}},"rightChild":{"id":29,"feature":6,"split":182.5,"leftChild":{"id":30,"prediction":[]},"rightChild":{"id":31,"prediction":[]}}}}},"rightChild":{"id":32,"feature":1,"split":0.22499999403953552,"leftChild":{"id":33,"feature":8,"split":2.9749999046325684,"leftChild":{"id":34,"feature":10,"split":9.149999618530273,"leftChild":{"id":35,"feature":6,"split":179.5,"leftChild":{"id":36,"prediction":[]},"rightChild":{"id":37,"prediction":[]}},"rightChild":{"id":38,"feature":3,"split":8.399999618530273,"leftChild":{"id":39,"prediction":[]},"rightChild":{"id":40,"prediction":[]}}},"rightChild":{"id":41,"feature":3,"split":5.525000095367432,"leftChild":{"id":42,"feature":10,"split":10.850000381469727,"leftChild":{"id":43,"prediction":[]},"rightChild":{"id":44,"prediction":[]}},"rightChild":{"id":45,"feature":0,"split":7.25,"leftChild":{"id":46,"prediction":[]},"rightChild":{"id":47,"prediction":[]}}}},"rightChild":{"id":48,"feature":0,"split":10.050000190734863,"leftChild":{"id":49,"feature":10,"split":10.725000381469727,"leftChild":{"id":50,"feature":2,"split":0.5450000166893005,"leftChild":{"id":51,"prediction":[]},"rightChild":{"id":52,"prediction":[]}},"rightChild":{"id":53,"feature":1,"split":0.4950000047683716,"leftChild":{"id":54,"prediction":[]},"rightChild":{"id":55,"prediction":[]}}},"rightChild":{"id":56,"feature":9,"split":0.6449999809265137,"leftChild":{"id":57,"feature":8,"split":3.2750000953674316,"leftChild":{"id":58,"prediction":[]},"rightChild":{"id":59,"prediction":[]}},"rightChild":{"id":60,"feature":8,"split":3.125,"leftChild":{"id":61,"prediction":[]},"rightChild":{"id":62,"prediction":[]}}}}}}},
{"patternid":14,"pattern":{"id":0,"feature":4,"split":0.03849999979138374,"leftChild":{"id":1,"feature":7,"split":0.991629958152771,"leftChild":{"id":2,"feature":1,"split":0.5249999761581421,"leftChild":{"id":3,"feature":3,"split":1.225000023841858,"leftChild":{"id":4,"feature":5,"split":10.5,"leftChild":{"id":5,"prediction":[]},"rightChild":{"id":6,"prediction":[]}},"rightChild":{"id":7,"feature":8,"split":3.0749998092651367,"leftChild":{"id":8,"prediction":[]},"rightChild":{"id":9,"prediction":[]}}},"rightChild":{"id":10,"feature":5,"split":25.0,"leftChild":{"id":11,"feature":4,"split":0.030499998480081558,"leftChild":{"id":12,"prediction":[]},"rightChild":{"id":13,"prediction":[]}},"rightChild":{"id":14,"feature":10,"split":12.549999237060547,"leftChild":{"id":15,"prediction":[]},"rightChild":{"id":16,"prediction":[]}}}},"rightChild":{"id":17,"feature":5,"split":16.5,"leftChild":{"id":18,"feature":3,"split":2.049999952316284,"leftChild":{"id":19,"feature":7,"split":0.9938000440597534,"leftChild":{"id":20,"prediction":[]},"rightChild":{"id":21,"prediction":[]}},"rightChild":{"id":22,"feature":5,"split":11.5,"leftChild":{"id":23,"prediction":[]},"rightChild":{"id":24,"prediction":[]}}},"rightChild":{"id":25,"feature":9,"split":0.3449999988079071,"leftChild":{"id":26,"feature":8,"split":3.3399999141693115,"leftChild":{"id":27,"prediction":[]},"rightChild":{"id":28,"prediction":[]}},"rightChild":{"id":29,"feature":6,"split":182.5,"leftChild":{"id":30,"prediction":[]},"rightChild":{"id":31,"prediction":[]}}}}},"rightChild":{"id":32,"feature":1,"split":0.22499999403953552,"leftChild":{"id":33,"feature":8,"split":2.9749999046325684,"leftChild":{"id":34,"feature":10,"split":9.149999618530273,"leftChild":{"id":35,"feature":6,"split":179.5,"leftChild":{"id":36,"prediction":[]},"rightChild":{"id":37,"prediction":[]}},"rightChild":{"id":38,"feature":3,"split":8.399999618530273,"leftChild":{"id":39,"prediction":[]},"rightChild":{"id":40,"prediction":[]}}},"rightChild":{"id":41,"feature":3,"split":5.525000095367432,"leftChild":{"id":42,"feature":10,"split":10.850000381469727,"leftChild":{"id":43,"prediction":[]},"rightChild":{"id":44,"prediction":[]}},"rightChild":{"id":45,"feature":0,"split":7.25,"leftChild":{"id":46,"prediction":[]},"rightChild":{"id":47,"prediction":[]}}}},"rightChild":{"id":48,"feature":0,"split":10.050000190734863,"leftChild":{"id":49,"feature":10,"split":10.725000381469727,"leftChild":{"id":50,"feature":2,"split":0.5450000166893005,"leftChild":{"id":51,"prediction":[]},"rightChild":{"id":52,"prediction":[]}},"rightChild":{"id":53,"feature":1,"split":0.4950000047683716,"leftChild":{"id":54,"prediction":[]},"rightChild":{"id":55,"prediction":[]}}},"rightChild":{"id":56,"feature":9,"split":0.6449999809265137,"leftChild":{"id":57,"feature":8,"split":3.2750000953674316,"leftChild":{"id":58,"prediction":[]},"rightChild":{"id":59,"prediction":[]}},"rightChild":{"id":60,"feature":8,"split":3.125,"leftChild":{"id":61,"prediction":[]},"rightChild":{"id":62,"prediction":[]}}}}}}},
{"patternid":15,"pattern":{"id":0,"feature":4,"split":0.03849999979138374,"leftChild":{"id":1,"feature":7,"split":0.991629958152771,"leftChild":{"id":2,"feature":1,"split":0.5249999761581421,"leftChild":{"id":3,"feature":3,"split":1.225000023841858,"leftChild":{"id":4,"feature":5,"split":10.5,"leftChild":{"id":5,"prediction":[]},"rightChild":{"id":6,"prediction":[]}},"rightChild":{"id":7,"feature":8,"split":3.0749998092651367,"leftChild":{"id":8,"prediction":[]},"rightChild":{"id":9,"prediction":[]}}},"rightChild":{"id":10,"feature":5,"split":25.0,"leftChild":{"id":11,"feature":4,"split":0.030499998480081558,"leftChild":{"id":12,"prediction":[]},"rightChild":{"id":13,"prediction":[]}},"rightChild":{"id":14,"feature":10,"split":12.549999237060547,"leftChild":{"id":15,"prediction":[]},"rightChild":{"id":16,"prediction":[]}}}},"rightChild":{"id":17,"feature":5,"split":16.5,"leftChild":{"id":18,"feature":3,"split":2.049999952316284,"leftChild":{"id":19,"feature":7,"split":0.9938000440597534,"leftChild":{"id":20,"prediction":[]},"rightChild":{"id":21,"prediction":[]}},"rightChild":{"id":22,"feature":5,"split":11.5,"leftChild":{"id":23,"prediction":[]},"rightChild":{"id":24,"prediction":[]}}},"rightChild":{"id":25,"feature":9,"split":0.3449999988079071,"leftChild":{"id":26,"feature":8,"split":3.3399999141693115,"leftChild":{"id":27,"prediction":[]},"rightChild":{"id":28,"prediction":[]}},"rightChild":{"id":29,"feature":6,"split":182.5,"leftChild":{"id":30,"prediction":[]},"rightChild":{"id":31,"prediction":[]}}}}},"rightChild":{"id":32,"feature":1,"split":0.22499999403953552,"leftChild":{"id":33,"feature":8,"split":2.9749999046325684,"leftChild":{"id":34,"feature":10,"split":9.149999618530273,"leftChild":{"id":35,"feature":6,"split":179.5,"leftChild":{"id":36,"prediction":[]},"rightChild":{"id":37,"prediction":[]}},"rightChild":{"id":38,"feature":3,"split":8.399999618530273,"leftChild":{"id":39,"prediction":[]},"rightChild":{"id":40,"prediction":[]}}},"rightChild":{"id":41,"feature":3,"split":5.525000095367432,"leftChild":{"id":42,"feature":10,"split":10.850000381469727,"leftChild":{"id":43,"prediction":[]},"rightChild":{"id":44,"prediction":[]}},"rightChild":{"id":45,"feature":0,"split":7.25,"leftChild":{"id":46,"prediction":[]},"rightChild":{"id":47,"prediction":[]}}}},"rightChild":{"id":48,"feature":0,"split":10.050000190734863,"leftChild":{"id":49,"feature":10,"split":10.725000381469727,"leftChild":{"id":50,"feature":2,"split":0.5450000166893005,"leftChild":{"id":51,"prediction":[]},"rightChild":{"id":52,"prediction":[]}},"rightChild":{"id":53,"feature":1,"split":0.4950000047683716,"leftChild":{"id":54,"prediction":[]},"rightChild":{"id":55,"prediction":[]}}},"rightChild":{"id":56,"feature":9,"split":0.6449999809265137,"leftChild":{"id":57,"feature":8,"split":3.2750000953674316,"leftChild":{"id":58,"prediction":[]},"rightChild":{"id":59,"prediction":[]}},"rightChild":{"id":60,"feature":8,"split":3.125,"leftChild":{"id":61,"prediction":[]},"rightChild":{"id":62,"prediction":[]}}}}}}},
{"patternid":16,"pattern":{"id":0,"feature":4,"split":0.03849999979138374,"leftChild":{"id":1,"feature":7,"split":0.991629958152771,"leftChild":{"id":2,"feature":1,"split":0.5249999761581421,"leftChild":{"id":3,"feature":3,"split":1.225000023841858,"leftChild":{"id":4,"feature":5,"split":10.5,"leftChild":{"id":5,"prediction":[]},"rightChild":{"id":6,"prediction":[]}},"rightChild":{"id":7,"feature":8,"split":3.0749998092651367,"leftChild":{"id":8,"prediction":[]},"rightChild":{"id":9,"prediction":[]}}},"rightChild":{"id":10,"feature":5,"split":25.0,"leftChild":{"id":11,"feature":4,"split":0.030499998480081558,"leftChild":{"id":12,"prediction":[]},"rightChild":{"id":13,"prediction":[]}},"rightChild":{"id":14,"feature":10,"split":12.549999237060547,"leftChild":{"id":15,"prediction":[]},"rightChild":{"id":16,"prediction":[]}}}},"rightChild":{"id":17,"feature":5,"split":16.5,"leftChild":{"id":18,"feature":3,"split":2.049999952316284,"leftChild":{"id":19,"feature":7,"split":0.9938000440597534,"leftChild":{"id":20,"prediction":[]},"rightChild":{"id":21,"prediction":[]}},"rightChild":{"id":22,"feature":5,"split":11.5,"leftChild":{"id":23,"prediction":[]},"rightChild":{"id":24,"prediction":[]}}},"rightChild":{"id":25,"feature":9,"split":0.3449999988079071,"leftChild":{"id":26,"feature":8,"split":3.3399999141693115,"leftChild":{"id":27,"prediction":[]},"rightChild":{"id":28,"prediction":[]}},"rightChild":{"id":29,"feature":6,"split":182.5,"leftChild":{"id":30,"prediction":[]},"rightChild":{"id":31,"prediction":[]}}}}},"rightChild":{"id":32,"feature":1,"split":0.22499999403953552,"leftChild":{"id":33,"feature":8,"split":2.9749999046325684,"leftChild":{"id":34,"feature":10,"split":9.149999618530273,"leftChild":{"id":35,"feature":6,"split":179.5,"leftChild":{"id":36,"prediction":[]},"rightChild":{"id":37,"prediction":[]}},"rightChild":{"id":38,"feature":3,"split":8.399999618530273,"leftChild":{"id":39,"prediction":[]},"rightChild":{"id":40,"prediction":[]}}},"rightChild":{"id":41,"feature":3,"split":5.525000095367432,"leftChild":{"id":42,"feature":10,"split":10.850000381469727,"leftChild":{"id":43,"prediction":[]},"rightChild":{"id":44,"prediction":[]}},"rightChild":{"id":45,"feature":0,"split":7.25,"leftChild":{"id":46,"prediction":[]},"rightChild":{"id":47,"prediction":[]}}}},"rightChild":{"id":48,"feature":0,"split":10.050000190734863,"leftChild":{"id":49,"feature":10,"split":10.725000381469727,"leftChild":{"id":50,"feature":2,"split":0.5450000166893005,"leftChild":{"id":51,"prediction":[]},"rightChild":{"id":52,"prediction":[]}},"rightChild":{"id":53,"feature":1,"split":0.4950000047683716,"leftChild":{"id":54,"prediction":[]},"rightChild":{"id":55,"prediction":[]}}},"rightChild":{"id":56,"feature":9,"split":0.6449999809265137,"leftChild":{"id":57,"feature":8,"split":3.2750000953674316,"leftChild":{"id":58,"prediction":[]},"rightChild":{"id":59,"prediction":[]}},"rightChild":{"id":60,"feature":8,"split":3.125,"leftChild":{"id":61,"prediction":[]},"rightChild":{"id":62,"prediction":[]}}}}}}},
{"patternid":17,"pattern":{"id":0,"feature":4,"split":0.03849999979138374,"leftChild":{"id":1,"feature":7,"split":0.991629958152771,"leftChild":{"id":2,"feature":1,"split":0.5249999761581421,"leftChild":{"id":3,"feature":3,"split":1.225000023841858,"leftChild":{"id":4,"feature":5,"split":10.5,"leftChild":{"id":5,"prediction":[]},"rightChild":{"id":6,"prediction":[]}},"rightChild":{"id":7,"feature":8,"split":3.0749998092651367,"leftChild":{"id":8,"prediction":[]},"rightChild":{"id":9,"prediction":[]}}},"rightChild":{"id":10,"feature":5,"split":25.0,"leftChild":{"id":11,"feature":4,"split":0.030499998480081558,"leftChild":{"id":12,"prediction":[]},"rightChild":{"id":13,"prediction":[]}},"rightChild":{"id":14,"feature":10,"split":12.549999237060547,"leftChild":{"id":15,"prediction":[]},"rightChild":{"id":16,"prediction":[]}}}},"rightChild":{"id":17,"feature":5,"split":16.5,"leftChild":{"id":18,"feature":3,"split":2.049999952316284,"leftChild":{"id":19,"feature":7,"split":0.9938000440597534,"leftChild":{"id":20,"prediction":[]},"rightChild":{"id":21,"prediction":[]}},"rightChild":{"id":22,"feature":5,"split":11.5,"leftChild":{"id":23,"prediction":[]},"rightChild":{"id":24,"prediction":[]}}},"rightChild":{"id":25,"feature":9,"split":0.3449999988079071,"leftChild":{"id":26,"feature":8,"split":3.3399999141693115,"leftChild":{"id":27,"prediction":[]},"rightChild":{"id":28,"prediction":[]}},"rightChild":{"id":29,"feature":6,"split":182.5,"leftChild":{"id":30,"prediction":[]},"rightChild":{"id":31,"prediction":[]}}}}},"rightChild":{"id":32,"feature":1,"split":0.22499999403953552,"leftChild":{"id":33,"feature":8,"split":2.9749999046325684,"leftChild":{"id":34,"feature":10,"split":9.149999618530273,"leftChild":{"id":35,"feature":6,"split":179.5,"leftChild":{"id":36,"prediction":[]},"rightChild":{"id":37,"prediction":[]}},"rightChild":{"id":38,"feature":3,"split":8.399999618530273,"leftChild":{"id":39,"prediction":[]},"rightChild":{"id":40,"prediction":[]}}},"rightChild":{"id":41,"feature":3,"split":5.525000095367432,"leftChild":{"id":42,"feature":10,"split":10.850000381469727,"leftChild":{"id":43,"prediction":[]},"rightChild":{"id":44,"prediction":[]}},"rightChild":{"id":45,"feature":0,"split":7.25,"leftChild":{"id":46,"prediction":[]},"rightChild":{"id":47,"prediction":[]}}}},"rightChild":{"id":48,"feature":0,"split":10.050000190734863,"leftChild":{"id":49,"feature":10,"split":10.725000381469727,"leftChild":{"id":50,"feature":2,"split":0.5450000166893005,"leftChild":{"id":51,"prediction":[]},"rightChild":{"id":52,"prediction":[]}},"rightChild":{"id":53,"feature":1,"split":0.4950000047683716,"leftChild":{"id":54,"prediction":[]},"rightChild":{"id":55,"prediction":[]}}},"rightChild":{"id":56,"feature":9,"split":0.6449999809265137,"leftChild":{"id":57,"feature":8,"split":3.2750000953674316,"leftChild":{"id":58,"prediction":[]},"rightChild":{"id":59,"prediction":[]}},"rightChild":{"id":60,"feature":8,"split":3.125,"leftChild":{"id":61,"prediction":[]},"rightChild":{"id":62,"prediction":[]}}}}}}},
{"patternid":18,"pattern":{"id":0,"feature":4,"split":0.03849999979138374,"leftChild":{"id":1,"feature":7,"split":0.991629958152771,"leftChild":{"id":2,"feature":1,"split":0.5249999761581421,"leftChild":{"id":3,"feature":3,"split":1.225000023841858,"leftChild":{"id":4,"feature":5,"split":10.5,"leftChild":{"id":5,"prediction":[]},"rightChild":{"id":6,"prediction":[]}},"rightChild":{"id":7,"feature":8,"split":3.0749998092651367,"leftChild":{"id":8,"prediction":[]},"rightChild":{"id":9,"prediction":[]}}},"rightChild":{"id":10,"feature":5,"split":25.0,"leftChild":{"id":11,"feature":4,"split":0.030499998480081558,"leftChild":{"id":12,"prediction":[]},"rightChild":{"id":13,"prediction":[]}},"rightChild":{"id":14,"feature":10,"split":12.549999237060547,"leftChild":{"id":15,"prediction":[]},"rightChild":{"id":16,"prediction":[]}}}},"rightChild":{"id":17,"feature":5,"split":16.5,"leftChild":{"id":18,"feature":3,"split":2.049999952316284,"leftChild":{"id":19,"feature":7,"split":0.9938000440597534,"leftChild":{"id":20,"prediction":[]},"rightChild":{"id":21,"prediction":[]}},"rightChild":{"id":22,"feature":5,"split":11.5,"leftChild":{"id":23,"prediction":[]},"rightChild":{"id":24,"prediction":[]}}},"rightChild":{"id":25,"feature":9,"split":0.3449999988079071,"leftChild":{"id":26,"feature":8,"split":3.3399999141693115,"leftChild":{"id":27,"prediction":[]},"rightChild":{"id":28,"prediction":[]}},"rightChild":{"id":29,"feature":6,"split":182.5,"leftChild":{"id":30,"prediction":[]},"rightChild":{"id":31,"prediction":[]}}}}},"rightChild":{"id":32,"feature":1,"split":0.22499999403953552,"leftChild":{"id":33,"feature":8,"split":2.9749999046325684,"leftChild":{"id":34,"feature":10,"split":9.149999618530273,"leftChild":{"id":35,"feature":6,"split":179.5,"leftChild":{"id":36,"prediction":[]},"rightChild":{"id":37,"prediction":[]}},"rightChild":{"id":38,"feature":3,"split":8.399999618530273,"leftChild":{"id":39,"prediction":[]},"rightChild":{"id":40,"prediction":[]}}},"rightChild":{"id":41,"feature":3,"split":5.525000095367432,"leftChild":{"id":42,"feature":10,"split":10.850000381469727,"leftChild":{"id":43,"prediction":[]},"rightChild":{"id":44,"prediction":[]}},"rightChild":{"id":45,"feature":0,"split":7.25,"leftChild":{"id":46,"prediction":[]},"rightChild":{"id":47,"prediction":[]}}}},"rightChild":{"id":48,"feature":0,"split":10.050000190734863,"leftChild":{"id":49,"feature":10,"split":10.725000381469727,"leftChild":{"id":50,"feature":2,"split":0.5450000166893005,"leftChild":{"id":51,"prediction":[]},"rightChild":{"id":52,"prediction":[]}},"rightChild":{"id":53,"feature":1,"split":0.4950000047683716,"leftChild":{"id":54,"prediction":[]},"rightChild":{"id":55,"prediction":[]}}},"rightChild":{"id":56,"feature":9,"split":0.6449999809265137,"leftChild":{"id":57,"feature":8,"split":3.2750000953674316,"leftChild":{"id":58,"prediction":[]},"rightChild":{"id":59,"prediction":[]}},"rightChild":{"id":60,"feature":8,"split":3.125,"leftChild":{"id":61,"prediction":[]},"rightChild":{"id":62,"prediction":[]}}}}}}},
{"patternid":19,"pattern":{"id":0,"feature":4,"split":0.03849999979138374,"leftChild":{"id":1,"feature":7,"split":0.991629958152771,"leftChild":{"id":2,"feature":1,"split":0.5249999761581421,"leftChild":{"id":3,"feature":3,"split":1.225000023841858,"leftChild":{"id":4,"feature":5,"split":10.5,"leftChild":{"id":5,"prediction":[]},"rightChild":{"id":6,"prediction":[]}},"rightChild":{"id":7,"feature":8,"split":3.0749998092651367,"leftChild":{"id":8,"prediction":[]},"rightChild":{"id":9,"prediction":[]}}},"rightChild":{"id":10,"feature":5,"split":25.0,"leftChild":{"id":11,"feature":4,"split":0.030499998480081558,"leftChild":{"id":12,"prediction":[]},"rightChild":{"id":13,"prediction":[]}},"rightChild":{"id":14,"feature":10,"split":12.549999237060547,"leftChild":{"id":15,"prediction":[]},"rightChild":{"id":16,"prediction":[]}}}},"rightChild":{"id":17,"feature":5,"split":16.5,"leftChild":{"id":18,"feature":3,"split":2.049999952316284,"leftChild":{"id":19,"feature":7,"split":0.9938000440597534,"leftChild":{"id":20,"prediction":[]},"rightChild":{"id":21,"prediction":[]}},"rightChild":{"id":22,"feature":5,"split":11.5,"leftChild":{"id":23,"prediction":[]},"rightChild":{"id":24,"prediction":[]}}},"rightChild":{"id":25,"feature":9,"split":0.3449999988079071,"leftChild":{"id":26,"feature":8,"split":3.3399999141693115,"leftChild":{"id":27,"prediction":[]},"rightChild":{"id":28,"prediction":[]}},"rightChild":{"id":29,"feature":6,"split":182.5,"leftChild":{"id":30,"prediction":[]},"rightChild":{"id":31,"prediction":[]}}}}},"rightChild":{"id":32,"feature":1,"split":0.22499999403953552,"leftChild":{"id":33,"feature":8,"split":2.9749999046325684,"leftChild":{"id":34,"feature":10,"split":9.149999618530273,"leftChild":{"id":35,"feature":6,"split":179.5,"leftChild":{"id":36,"prediction":[]},"rightChild":{"id":37,"prediction":[]}},"rightChild":{"id":38,"feature":3,"split":8.399999618530273,"leftChild":{"id":39,"prediction":[]},"rightChild":{"id":40,"prediction":[]}}},"rightChild":{"id":41,"feature":3,"split":5.525000095367432,"leftChild":{"id":42,"feature":10,"split":10.850000381469727,"leftChild":{"id":43,"prediction":[]},"rightChild":{"id":44,"prediction":[]}},"rightChild":{"id":45,"feature":0,"split":7.25,"leftChild":{"id":46,"prediction":[]},"rightChild":{"id":47,"prediction":[]}}}},"rightChild":{"id":48,"feature":0,"split":10.050000190734863,"leftChild":{"id":49,"feature":10,"split":10.725000381469727,"leftChild":{"id":50,"feature":2,"split":0.5450000166893005,"leftChild":{"id":51,"prediction":[]},"rightChild":{"id":52,"prediction":[]}},"rightChild":{"id":53,"feature":1,"split":0.4950000047683716,"leftChild":{"id":54,"prediction":[]},"rightChild":{"id":55,"prediction":[]}}},"rightChild":{"id":56,"feature":9,"split":0.6449999809265137,"leftChild":{"id":57,"feature":8,"split":3.2750000953674316,"leftChild":{"id":58,"prediction":[]},"rightChild":{"id":59,"prediction":[]}},"rightChild":{"id":60,"feature":8,"split":3.125,"leftChild":{"id":61,"prediction":[]},"rightChild":{"id":62,"prediction":[]}}}}}}},
{"patternid":20,"pattern":{"id":0,"feature":4,"split":0.03849999979138374,"leftChild":{"id":1,"feature":7,"split":0.991629958152771,"leftChild":{"id":2,"feature":1,"split":0.5249999761581421,"leftChild":{"id":3,"feature":3,"split":1.225000023841858,"leftChild":{"id":4,"feature":5,"split":10.5,"leftChild":{"id":5,"prediction":[]},"rightChild":{"id":6,"prediction":[]}},"rightChild":{"id":7,"feature":8,"split":3.0749998092651367,"leftChild":{"id":8,"prediction":[]},"rightChild":{"id":9,"prediction":[]}}},"rightChild":{"id":10,"feature":5,"split":25.0,"leftChild":{"id":11,"feature":4,"split":0.030499998480081558,"leftChild":{"id":12,"prediction":[]},"rightChild":{"id":13,"prediction":[]}},"rightChild":{"id":14,"feature":10,"split":12.549999237060547,"leftChild":{"id":15,"prediction":[]},"rightChild":{"id":16,"prediction":[]}}}},"rightChild":{"id":17,"feature":5,"split":16.5,"leftChild":{"id":18,"feature":3,"split":2.049999952316284,"leftChild":{"id":19,"feature":7,"split":0.9938000440597534,"leftChild":{"id":20,"prediction":[]},"rightChild":{"id":21,"prediction":[]}},"rightChild":{"id":22,"feature":5,"split":11.5,"leftChild":{"id":23,"prediction":[]},"rightChild":{"id":24,"prediction":[]}}},"rightChild":{"id":25,"feature":9,"split":0.3449999988079071,"leftChild":{"id":26,"feature":8,"split":3.3399999141693115,"leftChild":{"id":27,"prediction":[]},"rightChild":{"id":28,"prediction":[]}},"rightChild":{"id":29,"feature":6,"split":182.5,"leftChild":{"id":30,"prediction":[]},"rightChild":{"id":31,"prediction":[]}}}}},"rightChild":{"id":32,"feature":1,"split":0.22499999403953552,"leftChild":{"id":33,"feature":8,"split":2.9749999046325684,"leftChild":{"id":34,"feature":10,"split":9.149999618530273,"leftChild":{"id":35,"feature":6,"split":179.5,"leftChild":{"id":36,"prediction":[]},"rightChild":{"id":37,"prediction":[]}},"rightChild":{"id":38,"feature":3,"split":8.399999618530273,"leftChild":{"id":39,"prediction":[]},"rightChild":{"id":40,"prediction":[]}}},"rightChild":{"id":41,"feature":3,"split":5.525000095367432,"leftChild":{"id":42,"feature":10,"split":10.850000381469727,"leftChild":{"id":43,"prediction":[]},"rightChild":{"id":44,"prediction":[]}},"rightChild":{"id":45,"feature":0,"split":7.25,"leftChild":{"id":46,"prediction":[]},"rightChild":{"id":47,"prediction":[]}}}},"rightChild":{"id":48,"feature":0,"split":10.050000190734863,"leftChild":{"id":49,"feature":10,"split":10.725000381469727,"leftChild":{"id":50,"feature":2,"split":0.5450000166893005,"leftChild":{"id":51,"prediction":[]},"rightChild":{"id":52,"prediction":[]}},"rightChild":{"id":53,"feature":1,"split":0.4950000047683716,"leftChild":{"id":54,"prediction":[]},"rightChild":{"id":55,"prediction":[]}}},"rightChild":{"id":56,"feature":9,"split":0.6449999809265137,"leftChild":{"id":57,"feature":8,"split":3.2750000953674316,"leftChild":{"id":58,"prediction":[]},"rightChild":{"id":59,"prediction":[]}},"rightChild":{"id":60,"feature":8,"split":3.125,"leftChild":{"id":61,"prediction":[]},"rightChild":{"id":62,"prediction":[]}}}}}}},
{"patternid":21,"pattern":{"id":0,"feature":4,"split":0.03849999979138374,"leftChild":{"id":1,"feature":7,"split":0.991629958152771,"leftChild":{"id":2,"feature":1,"split":0.5249999761581421,"leftChild":{"id":3,"feature":3,"split":1.225000023841858,"leftChild":{"id":4,"feature":5,"split":10.5,"leftChild":{"id":5,"prediction":[]},"rightChild":{"id":6,"prediction":[]}},"rightChild":{"id":7,"feature":8,"split":3.0749998092651367,"leftChild":{"id":8,"prediction":[]},"rightChild":{"id":9,"prediction":[]}}},"rightChild":{"id":10,"feature":5,"split":25.0,"leftChild":{"id":11,"feature":4,"split":0.030499998480081558,"leftChild":{"id":12,"prediction":[]},"rightChild":{"id":13,"prediction":[]}},"rightChild":{"id":14,"feature":10,"split":12.549999237060547,"leftChild":{"id":15,"prediction":[]},"rightChild":{"id":16,"prediction":[]}}}},"rightChild":{"id":17,"feature":5,"split":16.5,"leftChild":{"id":18,"feature":3,"split":2.049999952316284,"leftChild":{"id":19,"feature":7,"split":0.9938000440597534,"leftChild":{"id":20,"prediction":[]},"rightChild":{"id":21,"prediction":[]}},"rightChild":{"id":22,"feature":5,"split":11.5,"leftChild":{"id":23,"prediction":[]},"rightChild":{"id":24,"prediction":[]}}},"rightChild":{"id":25,"feature":9,"split":0.3449999988079071,"leftChild":{"id":26,"feature":8,"split":3.3399999141693115,"leftChild":{"id":27,"prediction":[]},"rightChild":{"id":28,"prediction":[]}},"rightChild":{"id":29,"feature":6,"split":182.5,"leftChild":{"id":30,"prediction":[]},"rightChild":{"id":31,"prediction":[]}}}}},"rightChild":{"id":32,"feature":1,"split":0.22499999403953552,"leftChild":{"id":33,"feature":8,"split":2.9749999046325684,"leftChild":{"id":34,"feature":10,"split":9.149999618530273,"leftChild":{"id":35,"feature":6,"split":179.5,"leftChild":{"id":36,"prediction":[]},"rightChild":{"id":37,"prediction":[]}},"rightChild":{"id":38,"feature":3,"split":8.399999618530273,"leftChild":{"id":39,"prediction":[]},"rightChild":{"id":40,"prediction":[]}}},"rightChild":{"id":41,"feature":3,"split":5.525000095367432,"leftChild":{"id":42,"feature":10,"split":10.850000381469727,"leftChild":{"id":43,"prediction":[]},"rightChild":{"id":44,"prediction":[]}},"rightChild":{"id":45,"feature":0,"split":7.25,"leftChild":{"id":46,"prediction":[]},"rightChild":{"id":47,"prediction":[]}}}},"rightChild":{"id":48,"feature":0,"split":10.050000190734863,"leftChild":{"id":49,"feature":10,"split":10.725000381469727,"leftChild":{"id":50,"feature":2,"split":0.5450000166893005,"leftChild":{"id":51,"prediction":[]},"rightChild":{"id":52,"prediction":[]}},"rightChild":{"id":53,"feature":1,"split":0.4950000047683716,"leftChild":{"id":54,"prediction":[]},"rightChild":{"id":55,"prediction":[]}}},"rightChild":{"id":56,"feature":9,"split":0.6449999809265137,"leftChild":{"id":57,"feature":8,"split":3.2750000953674316,"leftChild":{"id":58,"prediction":[]},"rightChild":{"id":59,"prediction":[]}},"rightChild":{"id":60,"feature":8,"split":3.125,"leftChild":{"id":61,"prediction":[]},"rightChild":{"id":62,"prediction":[]}}}}}}},
{"patternid":22,"pattern":{"id":0,"feature":4,"split":0.03849999979138374,"leftChild":{"id":1,"feature":7,"split":0.991629958152771,"leftChild":{"id":2,"feature":1,"split":0.5249999761581421,"leftChild":{"id":3,"feature":3,"split":1.225000023841858,"leftChild":{"id":4,"feature":5,"split":10.5,"leftChild":{"id":5,"prediction":[]},"rightChild":{"id":6,"prediction":[]}},"rightChild":{"id":7,"feature":8,"split":3.0749998092651367,"leftChild":{"id":8,"prediction":[]},"rightChild":{"id":9,"prediction":[]}}},"rightChild":{"id":10,"feature":5,"split":25.0,"leftChild":{"id":11,"feature":4,"split":0.030499998480081558,"leftChild":{"id":12,"prediction":[]},"rightChild":{"id":13,"prediction":[]}},"rightChild":{"id":14,"feature":10,"split":12.549999237060547,"leftChild":{"id":15,"prediction":[]},"rightChild":{"id":16,"prediction":[]}}}},"rightChild":{"id":17,"feature":5,"split":16.5,"leftChild":{"id":18,"feature":3,"split":2.049999952316284,"leftChild":{"id":19,"feature":7,"split":0.9938000440597534,"leftChild":{"id":20,"prediction":[]},"rightChild":{"id":21,"prediction":[]}},"rightChild":{"id":22,"feature":5,"split":11.5,"leftChild":{"id":23,"prediction":[]},"rightChild":{"id":24,"prediction":[]}}},"rightChild":{"id":25,"feature":9,"split":0.3449999988079071,"leftChild":{"id":26,"feature":8,"split":3.3399999141693115,"leftChild":{"id":27,"prediction":[]},"rightChild":{"id":28,"prediction":[]}},"rightChild":{"id":29,"feature":6,"split":182.5,"leftChild":{"id":30,"prediction":[]},"rightChild":{"id":31,"prediction":[]}}}}},"rightChild":{"id":32,"feature":1,"split":0.22499999403953552,"leftChild":{"id":33,"feature":8,"split":2.9749999046325684,"leftChild":{"id":34,"feature":10,"split":9.149999618530273,"leftChild":{"id":35,"feature":6,"split":179.5,"leftChild":{"id":36,"prediction":[]},"rightChild":{"id":37,"prediction":[]}},"rightChild":{"id":38,"feature":3,"split":8.399999618530273,"leftChild":{"id":39,"prediction":[]},"rightChild":{"id":40,"prediction":[]}}},"rightChild":{"id":41,"feature":3,"split":5.525000095367432,"leftChild":{"id":42,"feature":10,"split":10.850000381469727,"leftChild":{"id":43,"prediction":[]},"rightChild":{"id":44,"prediction":[]}},"rightChild":{"id":45,"feature":0,"split":7.25,"leftChild":{"id":46,"prediction":[]},"rightChild":{"id":47,"prediction":[]}}}},"rightChild":{"id":48,"feature":0,"split":10.050000190734863,"leftChild":{"id":49,"feature":10,"split":10.725000381469727,"leftChild":{"id":50,"feature":2,"split":0.5450000166893005,"leftChild":{"id":51,"prediction":[]},"rightChild":{"id":52,"prediction":[]}},"rightChild":{"id":53,"feature":1,"split":0.4950000047683716,"leftChild":{"id":54,"prediction":[]},"rightChild":{"id":55,"prediction":[]}}},"rightChild":{"id":56,"feature":9,"split":0.6449999809265137,"leftChild":{"id":57,"feature":8,"split":3.2750000953674316,"leftChild":{"id":58,"prediction":[]},"rightChild":{"id":59,"prediction":[]}},"rightChild":{"id":60,"feature":8,"split":3.125,"leftChild":{"id":61,"prediction":[]},"rightChild":{"id":62,"prediction":[]}}}}}}},
{"patternid":23,"pattern":{"id":0,"feature":4,"split":0.03849999979138374,"leftChild":{"id":1,"feature":7,"split":0.991629958152771,"leftChild":{"id":2,"feature":1,"split":0.5249999761581421,"leftChild":{"id":3,"feature":3,"split":1.225000023841858,"leftChild":{"id":4,"feature":5,"split":10.5,"leftChild":{"id":5,"prediction":[]},"rightChild":{"id":6,"prediction":[]}},"rightChild":{"id":7,"feature":8,"split":3.0749998092651367,"leftChild":{"id":8,"prediction":[]},"rightChild":{"id":9,"prediction":[]}}},"rightChild":{"id":10,"feature":5,"split":25.0,"leftChild":{"id":11,"feature":4,"split":0.030499998480081558,"leftChild":{"id":12,"prediction":[]},"rightChild":{"id":13,"prediction":[]}},"rightChild":{"id":14,"feature":10,"split":12.549999237060547,"leftChild":{"id":15,"prediction":[]},"rightChild":{"id":16,"prediction":[]}}}},"rightChild":{"id":17,"feature":5,"split":16.5,"leftChild":{"id":18,"feature":3,"split":2.049999952316284,"leftChild":{"id":19,"feature":7,"split":0.9938000440597534,"leftChild":{"id":20,"prediction":[]},"rightChild":{"id":21,"prediction":[]}},"rightChild":{"id":22,"feature":5,"split":11.5,"leftChild":{"id":23,"prediction":[]},"rightChild":{"id":24,"prediction":[]}}},"rightChild":{"id":25,"feature":9,"split":0.3449999988079071,"leftChild":{"id":26,"feature":8,"split":3.3399999141693115,"leftChild":{"id":27,"prediction":[]},"rightChild":{"id":28,"prediction":[]}},"rightChild":{"id":29,"feature":6,"split":182.5,"leftChild":{"id":30,"prediction":[]},"rightChild":{"id":31,"prediction":[]}}}}},"rightChild":{"id":32,"feature":1,"split":0.22499999403953552,"leftChild":{"id":33,"feature":8,"split":2.9749999046325684,"leftChild":{"id":34,"feature":10,"split":9.149999618530273,"leftChild":{"id":35,"feature":6,"split":179.5,"leftChild":{"id":36,"prediction":[]},"rightChild":{"id":37,"prediction":[]}},"rightChild":{"id":38,"feature":3,"split":8.399999618530273,"leftChild":{"id":39,"prediction":[]},"rightChild":{"id":40,"prediction":[]}}},"rightChild":{"id":41,"feature":3,"split":5.525000095367432,"leftChild":{"id":42,"feature":10,"split":10.850000381469727,"leftChild":{"id":43,"prediction":[]},"rightChild":{"id":44,"prediction":[]}},"rightChild":{"id":45,"feature":0,"split":7.25,"leftChild":{"id":46,"prediction":[]},"rightChild":{"id":47,"prediction":[]}}}},"rightChild":{"id":48,"feature":0,"split":10.050000190734863,"leftChild":{"id":49,"feature":10,"split":10.725000381469727,"leftChild":{"id":50,"feature":2,"split":0.5450000166893005,"leftChild":{"id":51,"prediction":[]},"rightChild":{"id":52,"prediction":[]}},"rightChild":{"id":53,"feature":1,"split":0.4950000047683716,"leftChild":{"id":54,"prediction":[]},"rightChild":{"id":55,"prediction":[]}}},"rightChild":{"id":56,"feature":9,"split":0.6449999809265137,"leftChild":{"id":57,"feature":8,"split":3.2750000953674316,"leftChild":{"id":58,"prediction":[]},"rightChild":{"id":59,"prediction":[]}},"rightChild":{"id":60,"feature":8,"split":3.125,"leftChild":{"id":61,"prediction":[]},"rightChild":{"id":62,"prediction":[]}}}}}}},
{"patternid":24,"pattern":{"id":0,"feature":4,"split":0.03849999979138374,"leftChild":{"id":1,"feature":7,"split":0.991629958152771,"leftChild":{"id":2,"feature":1,"split":0.5249999761581421,"leftChild":{"id":3,"feature":3,"split":1.225000023841858,"leftChild":{"id":4,"feature":5,"split":10.5,"leftChild":{"id":5,"prediction":[]},"rightChild":{"id":6,"prediction":[]}},"rightChild":{"id":7,"feature":8,"split":3.0749998092651367,"leftChild":{"id":8,"prediction":[]},"rightChild":{"id":9,"prediction":[]}}},"rightChild":{"id":10,"feature":5,"split":25.0,"leftChild":{"id":11,"feature":4,"split":0.030499998480081558,"leftChild":{"id":12,"prediction":[]},"rightChild":{"id":13,"prediction":[]}},"rightChild":{"id":14,"feature":10,"split":12.549999237060547,"leftChild":{"id":15,"prediction":[]},"rightChild":{"id":16,"prediction":[]}}}},"rightChild":{"id":17,"feature":5,"split":16.5,"leftChild":{"id":18,"feature":3,"split":2.049999952316284,"leftChild":{"id":19,"feature":7,"split":0.9938000440597534,"leftChild":{"id":20,"prediction":[]},"rightChild":{"id":21,"prediction":[]}},"rightChild":{"id":22,"feature":5,"split":11.5,"leftChild":{"id":23,"prediction":[]},"rightChild":{"id":24,"prediction":[]}}},"rightChild":{"id":25,"feature":9,"split":0.3449999988079071,"leftChild":{"id":26,"feature":8,"split":3.3399999141693115,"leftChild":{"id":27,"prediction":[]},"rightChild":{"id":28,"prediction":[]}},"rightChild":{"id":29,"feature":6,"split":182.5,"leftChild":{"id":30,"prediction":[]},"rightChild":{"id":31,"prediction":[]}}}}},"rightChild":{"id":32,"feature":1,"split":0.22499999403953552,"leftChild":{"id":33,"feature":8,"split":2.9749999046325684,"leftChild":{"id":34,"feature":10,"split":9.149999618530273,"leftChild":{"id":35,"feature":6,"split":179.5,"leftChild":{"id":36,"prediction":[]},"rightChild":{"id":37,"prediction":[]}},"rightChild":{"id":38,"feature":3,"split":8.399999618530273,"leftChild":{"id":39,"prediction":[]},"rightChild":{"id":40,"prediction":[]}}},"rightChild":{"id":41,"feature":3,"split":5.525000095367432,"leftChild":{"id":42,"feature":10,"split":10.850000381469727,"leftChild":{"id":43,"prediction":[]},"rightChild":{"id":44,"prediction":[]}},"rightChild":{"id":45,"feature":0,"split":7.25,"leftChild":{"id":46,"prediction":[]},"rightChild":{"id":47,"prediction":[]}}}},"rightChild":{"id":48,"feature":0,"split":10.050000190734863,"leftChild":{"id":49,"feature":10,"split":10.725000381469727,"leftChild":{"id":50,"feature":2,"split":0.5450000166893005,"leftChild":{"id":51,"prediction":[]},"rightChild":{"id":52,"prediction":[]}},"rightChild":{"id":53,"feature":1,"split":0.4950000047683716,"leftChild":{"id":54,"prediction":[]},"rightChild":{"id":55,"prediction":[]}}},"rightChild":{"id":56,"feature":9,"split":0.6449999809265137,"leftChild":{"id":57,"feature":8,"split":3.2750000953674316,"leftChild":{"id":58,"prediction":[]},"rightChild":{"id":59,"prediction":[]}},"rightChild":{"id":60,"feature":8,"split":3.125,"leftChild":{"id":61,"prediction":[]},"rightChild":{"id":62,"prediction":[]}}}}}}},
{"patternid":25,"pattern":{"id":0,"feature":4,"split":0.03849999979138374,"leftChild":{"id":1,"feature":7,"split":0.991629958152771,"leftChild":{"id":2,"feature":1,"split":0.5249999761581421,"leftChild":{"id":3,"feature":3,"split":1.225000023841858,"leftChild":{"id":4,"feature":5,"split":10.5,"leftChild":{"id":5,"prediction":[]},"rightChild":{"id":6,"prediction":[]}},"rightChild":{"id":7,"feature":8,"split":3.0749998092651367,"leftChild":{"id":8,"prediction":[]},"rightChild":{"id":9,"prediction":[]}}},"rightChild":{"id":10,"feature":5,"split":25.0,"leftChild":{"id":11,"feature":4,"split":0.030499998480081558,"leftChild":{"id":12,"prediction":[]},"rightChild":{"id":13,"prediction":[]}},"rightChild":{"id":14,"feature":10,"split":12.549999237060547,"leftChild":{"id":15,"prediction":[]},"rightChild":{"id":16,"prediction":[]}}}},"rightChild":{"id":17,"feature":5,"split":16.5,"leftChild":{"id":18,"feature":3,"split":2.049999952316284,"leftChild":{"id":19,"feature":7,"split":0.9938000440597534,"leftChild":{"id":20,"prediction":[]},"rightChild":{"id":21,"prediction":[]}},"rightChild":{"id":22,"feature":5,"split":11.5,"leftChild":{"id":23,"prediction":[]},"rightChild":{"id":24,"prediction":[]}}},"rightChild":{"id":25,"feature":9,"split":0.3449999988079071,"leftChild":{"id":26,"feature":8,"split":3.3399999141693115,"leftChild":{"id":27,"prediction":[]},"rightChild":{"id":28,"prediction":[]}},"rightChild":{"id":29,"feature":6,"split":182.5,"leftChild":{"id":30,"prediction":[]},"rightChild":{"id":31,"prediction":[]}}}}},"rightChild":{"id":32,"feature":1,"split":0.22499999403953552,"leftChild":{"id":33,"feature":8,"split":2.9749999046325684,"leftChild":{"id":34,"feature":10,"split":9.149999618530273,"leftChild":{"id":35,"feature":6,"split":179.5,"leftChild":{"id":36,"prediction":[]},"rightChild":{"id":37,"prediction":[]}},"rightChild":{"id":38,"feature":3,"split":8.399999618530273,"leftChild":{"id":39,"prediction":[]},"rightChild":{"id":40,"prediction":[]}}},"rightChild":{"id":41,"feature":3,"split":5.525000095367432,"leftChild":{"id":42,"feature":10,"split":10.850000381469727,"leftChild":{"id":43,"prediction":[]},"rightChild":{"id":44,"prediction":[]}},"rightChild":{"id":45,"feature":0,"split":7.25,"leftChild":{"id":46,"prediction":[]},"rightChild":{"id":47,"prediction":[]}}}},"rightChild":{"id":48,"feature":0,"split":10.050000190734863,"leftChild":{"id":49,"feature":10,"split":10.725000381469727,"leftChild":{"id":50,"feature":2,"split":0.5450000166893005,"leftChild":{"id":51,"prediction":[]},"rightChild":{"id":52,"prediction":[]}},"rightChild":{"id":53,"feature":1,"split":0.4950000047683716,"leftChild":{"id":54,"prediction":[]},"rightChild":{"id":55,"prediction":[]}}},"rightChild":{"id":56,"feature":9,"split":0.6449999809265137,"leftChild":{"id":57,"feature":8,"split":3.2750000953674316,"leftChild":{"id":58,"prediction":[]},"rightChild":{"id":59,"prediction":[]}},"rightChild":{"id":60,"feature":8,"split":3.125,"leftChild":{"id":61,"prediction":[]},"rightChild":{"id":62,"prediction":[]}}}}}}}]